Workbook

Sheet P&L
A1: Alino Property Ltd
A2: Draft Profit and Loss Account – period 17/07/2025 to 17/02/2026 (records provided)
A3: =IF(Notes!B4="Yes","Includes rent-split payments (Apr-25 – Mar-26) – see Notes","Excludes rent-split payments – see Notes switch") -> Excludes rent-split payments – see Notes switch
B5: £ | C5: £
A6: Turnover
A7: Rental income | B7: =-SUMIFS('Trial Balance'!$E:$E,'Trial Balance'!$A:$A,"Rental income") -> 2200
A8: Building work income | B8: =-SUMIFS('Trial Balance'!$E:$E,'Trial Balance'!$A:$A,"Building work income") -> 4000
A9: Other income (purpose to confirm) | B9: =-SUMIFS('Trial Balance'!$E:$E,'Trial Balance'!$A:$A,"Other income (to confirm)") -> 7132
A10: Total turnover | C10: =SUM(B7:B9) -> 13332
A12: Cost of sales
A13: Subcontractor / building costs | B13: =SUMIFS('Trial Balance'!$E:$E,'Trial Balance'!$A:$A,"Subcontractor / building costs") -> 2200
A14: Rent payable (rent-to-rent properties) | B14: =SUMIFS('Trial Balance'!$E:$E,'Trial Balance'!$A:$A,"Rent payable") -> 0
A15: Total cost of sales | C15: =SUM(B13:B14) -> 2200
A17: Gross profit / (loss) | C17: =C10-C15 -> 11132
A19: Administrative expenses
A20: Repairs & maintenance (Seyat Can materials) | B20: =SUMIFS('Trial Balance'!$E:$E,'Trial Balance'!$A:$A,"Repairs & maintenance") -> 0
A21: Tenancy set-up costs (Goodlord) | B21: =SUMIFS('Trial Balance'!$E:$E,'Trial Balance'!$A:$A,"Tenancy set-up costs (Goodlord)") -> 0
A22: Sundry expenses (IW Group Services) | B22: =SUMIFS('Trial Balance'!$E:$E,'Trial Balance'!$A:$A,"Sundry expenses (IW Group Services)") -> 0
A23: Total administrative expenses | C23: =SUM(B20:B22) -> 0
A25: Operating profit / (loss) | C25: =C17-C23 -> 11132
A27: Interest payable and similar charges
A28: Mortgage interest – Together Commercial | B28: =SUMIFS('Trial Balance'!$E:$E,'Trial Balance'!$A:$A,"Mortgage interest") -> 16502.05
A29: Loan arrangement & remortgage costs | B29: =SUMIFS('Trial Balance'!$E:$E,'Trial Balance'!$A:$A,"Loan arrangement & remortgage costs") -> 2385
A30: Total finance costs | C30: =SUM(B28:B29) -> 18887.05
A32: Profit / (loss) before tax | C32: =C25-C30 -> -7755.05
A34: Corporation tax (none – loss; losses carried forward) | C34: =0 -> 0
A35: Profit / (loss) for the period | C35: =C32-C34 -> -7755.05
A37: Check: P&L result = Trial Balance income − expenses (must be 0) | C37: =ROUND(C35+SUMIFS('Trial Balance'!$E:$E,'Trial Balance'!$B:$B,"Income")+SUMIFS('Trial Balance'!$E:$E,'Trial Balance'!$B:$B,"Expense"),2) -> 0

Sheet Balance Sheet
A1: Alino Property Ltd
A2: Draft Balance Sheet as at 17/02/2026
A3: ='P&L'!A3 -> Excludes rent-split payments – see Notes switch
B5: £ | C5: £
A6: Fixed assets
A7: Investment property – 36 Cairnsford Road (cost) | B7: =SUMIFS('Trial Balance'!$E:$E,'Trial Balance'!$A:$A,"Investment property – 36 Cairnsford Rd") -> 499943.94
A8: Improvements – 36 Cairnsford Road (Seyat Can materials) | B8: =SUMIFS('Trial Balance'!$E:$E,'Trial Balance'!$A:$A,"Property improvements – 36 Cairnsford Rd") -> 4500
A9: Investment property – 30 Strensall Road (cost – see Notes) | B9: =SUMIFS('Trial Balance'!$E:$E,'Trial Balance'!$A:$A,"Investment property – 30 Strensall Rd") -> 0
C10: =SUM(B7:B9) -> 504443.94
A12: Current assets
A13: Cash at bank – Monzo | B13: =SUMIFS('Trial Balance'!$E:$E,'Trial Balance'!$A:$A,"Cash at bank – Monzo") -> 129.95
A14: Cash at bank – other (share capital, not traced) | B14: =SUMIFS('Trial Balance'!$E:$E,'Trial Balance'!$A:$A,"Cash at bank – share capital not traced") -> 0
C15: =SUM(B13:B14) -> 129.95
A16: Creditors: amounts falling due within one year
A17: Director's loan account – Alvine Tchega | B17: =-SUMIFS('Trial Balance'!$E:$E,'Trial Balance'!$A:$A,"Director's loan – Alvine Tchega") -> 21462.34
A18: Loan – Kakmeni | B18: =-SUMIFS('Trial Balance'!$E:$E,'Trial Balance'!$A:$A,"Loan – Kakmeni") -> 39000
A19: Loan – The Kulture Bar | B19: =-SUMIFS('Trial Balance'!$E:$E,'Trial Balance'!$A:$A,"Loan – The Kulture Bar") -> 6400
A20: Suspense – other bank account (not provided) | B20: =-SUMIFS('Trial Balance'!$E:$E,'Trial Balance'!$A:$A,"Suspense – other bank account (not provided)") -> 0
C21: =-SUM(B17:B20) -> -66862.34
A23: Net current assets / (liabilities) | C23: =C15+C21 -> -66732.39
A25: Total assets less current liabilities | C25: =C10+C23 -> 437711.55
A27: Creditors: amounts falling due after more than one year
A28: Mortgage – Together Commercial (36 Cairnsford Rd) | B28: =-SUMIFS('Trial Balance'!$E:$E,'Trial Balance'!$A:$A,"Mortgage – Together Commercial (Cairnsford)") -> 311938.6
A29: Mortgage – Together Commercial (30 Strensall Rd) | B29: =-SUMIFS('Trial Balance'!$E:$E,'Trial Balance'!$A:$A,"Mortgage – Together Commercial (Strensall)") -> 133528
C30: =-SUM(B28:B29) -> -445466.6
A32: Net assets / (liabilities) | C32: =C25+C30 -> -7755.05
A34: Capital and reserves
A35: Called-up share capital | B35: =-SUMIFS('Trial Balance'!$E:$E,'Trial Balance'!$A:$A,"Share capital") -> 0
A36: Profit and loss account | B36: ='P&L'!C35 -> -7755.05
A37: Shareholders' funds / (deficit) | C37: =SUM(B35:B36) -> -7755.05
A39: Check: net assets − shareholders' funds (must be 0) | C39: =ROUND(C32-C37,2) -> 0
A41: Draft prepared from bank statements and completion statements only. Not reviewed by an accountant; see the Notes sheet for assumptions.

Sheet Notes
A1: Alino Property Ltd – Draft Accounts: Notes, Inputs & Assumptions
A3: Inputs (yellow cells can be changed)
A4: Include rent-split payments (rent_split.xlsx) in these accounts? | B4: No | C4: Choose Yes/No. Those 99 payments came from a different bank account, which wasn't provided, and the payer isn't confirmed as Alino Property Ltd.
A5: Rent payable – rent_split.xlsx rent subtotal | B5: 133385.92 | C5: Source: rent_split.xlsx › Summary › Rent subtotal (11 properties, Apr-25 to Mar-26)
A6: Goodlord payments – rent_split.xlsx | B6: 7712 | C6: Source: rent_split.xlsx › Summary › Goodlord
A7: IW Group Services UK – rent_split.xlsx | B7: 1511.47 | C7: Source: rent_split.xlsx › Summary › IW Group Services
A8: Share capital (£) | B8: 0 | C8: Not provided – enter from Companies House confirmation statement
A9: Cost of 30 Strensall Road (£) | B9: 0 | C9: Not provided – company appears to own it (MR01 charge registered); enter original cost
A10: Seyat Can materials £4,500 – treatment | B10: Asset | C10: Asset = improvement to 36 Cairnsford Rd (balance sheet). Repairs = repairs & maintenance expense (P&L). Choose from the list.
A12: Records used
A13: • Monzo business account 22148285 (Alino Property Ltd): 01/09/2025 – 17/02/2026. Sep–Nov checked to PDF statements; Dec–Feb from Monzo export only.
A14: • Completion statement – remortgage of 30 Strensall Road, Leicester LE2 9FT, completed 17/07/2025.
A15: • Completion statement (DWS Legal) – purchase of 36 Cairnsford Road, Leicester LE2 6GF, completed 17/07/2025, funded by Together Commercial Finance.
A16: • Optional: rent-split payments (rent_split.xlsx) – only if the switch above is set to Yes.
A18: Assumptions – please review
A19: 1. Period: from 17/07/2025 (completions) to 17/02/2026 (last bank record). The year-end isn't known. Mar-26 mortgage payments and any Aug/Sep-25 payments aren't in the records.
A20: 2. Opening position: Monzo opened with £0.00 on 01/09/2025. No prior-year balance sheet was provided, so opening reserves are taken as nil.
A21: 3. Mortgage loans are recorded at the net advance shown on the completion statements. The gross loan and any lender fees deducted need the Together Commercial offer letters.
A22: 4. Together Commercial direct debits are all treated as interest (interest-only commercial loans). If any part repays capital, move it to the loan balance.
A23: 5. Loan arrangement and remortgage costs (£2,385) are expensed in full. Strictly, under FRS 102 they are spread over the loan term.
A24: 6. VAT on fees is treated as irrecoverable, because the company is assumed not to be VAT-registered.
... A31: 13. If the rent-split switch is Yes, the other bank account's balance is unknown. The payments are then funded through a suspense account until that bank statement is provided.

Sheet Trial Balance
A1: Account | B1: Type | C1: Debit (£) | D1: Credit (£) | E1: Net Dr/(Cr) (£)
A2: Investment property – 36 Cairnsford Rd | B2: Asset | C2: =IF(E2>0,E2,0) -> 499943.94 | D2: =IF(E2<0,-E2,0) -> 0 | E2: =SUMIFS(Journals!$E:$E,Journals!$D:$D,$A2)-SUMIFS(Journals!$F:$F,Journals!$D:$D,$A2) -> 499943.94
A3: Investment property – 30 Strensall Rd | B3: Asset | C3: =IF(E3>0,E3,0) -> 0 | D3: =IF(E3<0,-E3,0) -> 0 | E3: =SUMIFS(Journals!$E:$E,Journals!$D:$D,$A3)-SUMIFS(Journals!$F:$F,Journals!$D:$D,$A3) -> 0
A4: Property improvements – 36 Cairnsford Rd | B4: Asset | C4: =IF(E4>0,E4,0) -> 4500 | D4: =IF(E4<0,-E4,0) -> 0 | E4: =SUMIFS(Journals!$E:$E,Journals!$D:$D,$A4)-SUMIFS(Journals!$F:$F,Journals!$D:$D,$A4) -> 4500
A5: Cash at bank – Monzo | B5: Asset | C5: =IF(E5>0,E5,0) -> 129.95 | D5: =IF(E5<0,-E5,0) -> 0 | E5: =SUMIFS(Journals!$E:$E,Journals!$D:$D,$A5)-SUMIFS(Journals!$F:$F,Journals!$D:$D,$A5) -> 129.95
A6: Cash at bank – share capital not traced | B6: Asset | C6: =IF(E6>0,E6,0) -> 0 | D6: =IF(E6<0,-E6,0) -> 0 | E6: =SUMIFS(Journals!$E:$E,Journals!$D:$D,$A6)-SUMIFS(Journals!$F:$F,Journals!$D:$D,$A6) -> 0
A7: Mortgage – Together Commercial (Cairnsford) | B7: Liability | C7: =IF(E7>0,E7,0) -> 0 | D7: =IF(E7<0,-E7,0) -> 311938.6 | E7: =SUMIFS(Journals!$E:$E,Journals!$D:$D,$A7)-SUMIFS(Journals!$F:$F,Journals!$D:$D,$A7) -> -311938.6
A8: Mortgage – Together Commercial (Strensall) | B8: Liability | C8: =IF(E8>0,E8,0) -> 0 | D8: =IF(E8<0,-E8,0) -> 133528 | E8: =SUMIFS(Journals!$E:$E,Journals!$D:$D,$A8)-SUMIFS(Journals!$F:$F,Journals!$D:$D,$A8) -> -133528
A9: Director's loan – Alvine Tchega | B9: Liability | C9: =IF(E9>0,E9,0) -> 0 | D9: =IF(E9<0,-E9,0) -> 21462.34 | E9: =SUMIFS(Journals!$E:$E,Journals!$D:$D,$A9)-SUMIFS(Journals!$F:$F,Journals!$D:$D,$A9) -> -21462.34
A10: Loan – Kakmeni | B10: Liability | C10: =IF(E10>0,E10,0) -> 0 | D10: =IF(E10<0,-E10,0) -> 39000 | E10: =SUMIFS(Journals!$E:$E,Journals!$D:$D,$A10)-SUMIFS(Journals!$F:$F,Journals!$D:$D,$A10) -> -39000
A11: Loan – The Kulture Bar | B11: Liability | C11: =IF(E11>0,E11,0) -> 0 | D11: =IF(E11<0,-E11,0) -> 6400 | E11: =SUMIFS(Journals!$E:$E,Journals!$D:$D,$A11)-SUMIFS(Journals!$F:$F,Journals!$D:$D,$A11) -> -6400
A12: Suspense – other bank account (not provided) | B12: Liability | C12: =IF(E12>0,E12,0) -> 0 | D12: =IF(E12<0,-E12,0) -> 0 | E12: =SUMIFS(Journals!$E:$E,Journals!$D:$D,$A12)-SUMIFS(Journals!$F:$F,Journals!$D:$D,$A12) -> 0
A13: Share capital | B13: Equity | C13: =IF(E13>0,E13,0) -> 0 | D13: =IF(E13<0,-E13,0) -> 0 | E13: =SUMIFS(Journals!$E:$E,Journals!$D:$D,$A13)-SUMIFS(Journals!$F:$F,Journals!$D:$D,$A13) -> 0
... A23: Loan arrangement & remortgage costs | B23: Expense | C23: =IF(E23>0,E23,0) -> 2385 | D23: =IF(E23<0,-E23,0) -> 0 | E23: =SUMIFS(Journals!$E:$E,Journals!$D:$D,$A23)-SUMIFS(Journals!$F:$F,Journals!$D:$D,$A23) -> 2385
A24: Totals | C24: =SUM(C2:C23) -> 525660.94 | D24: =SUM(D2:D23) -> 525660.94 | E24: =SUM(E2:E23) -> 2.5465852e-11
A25: Unmapped journal lines (must be 0) | E25: =ROUND(SUM(Journals!E2:E35)-SUM(Journals!F2:F35)-E24,2) -> 0
A26: Monzo balance check vs statement 17/02/2026 £129.95 (must be 0) | E26: =ROUND(E5-'Monzo Reconciliation'!F10,2) -> 0

Sheet Journals
A1: # | B1: Date | C1: Description | D1: Account | E1: Debit (£) | F1: Credit (£) | G1: Source
A2: 1 | B2: 17/07/2025 | C2: Purchase of 36 Cairnsford Rd – price, SDLT & acquisition fees | D2: Investment property – 36 Cairnsford Rd | E2: =SUMIFS('Completion Lines'!$F:$F,'Completion Lines'!$G:$G,"Property cost – purchase price")+SUMIFS('Completion Lines'!$F:$F,'Completion Lines'!$G:$G,"Property cost – Stamp Duty (SDLT)")+SUMIFS('Completion Lines'!$F:$F,'Completion Lines'!$G:$G,"Property cost – legal & acquisition fees") -> 499943.94 | F2: 0 | G2: Completion Lines
A3: 2 | B3: 17/07/2025 | C3: Lender fees – Cairnsford mortgage | D3: Loan arrangement & remortgage costs | E3: =SUMIFS('Completion Lines'!$F:$F,'Completion Lines'!$G:$G,"Finance cost – Cairnsford mortgage") -> 715 | F3: 0 | G3: Completion Lines
A4: 3 | B4: 17/07/2025 | C4: Remortgage costs – 30 Strensall Rd | D4: Loan arrangement & remortgage costs | E4: =SUMIFS('Completion Lines'!$F:$F,'Completion Lines'!$G:$G,"Finance cost – Strensall remortgage") -> 1670 | F4: 0 | G4: Completion Lines
A5: 4 | B5: 17/07/2025 | C5: Together Commercial advance – Cairnsford (net) | D5: Mortgage – Together Commercial (Cairnsford) | E5: 0 | F5: =SUMIFS('Completion Lines'!$C:$C,'Completion Lines'!$G:$G,"Funding – Together Commercial mortgage (net)") -> 311938.6 | G5: Completion Lines
A6: 5 | B6: 17/07/2025 | C6: Together Commercial advance – Strensall remortgage (net) | D6: Mortgage – Together Commercial (Strensall) | E6: 0 | F6: =SUMIFS('Completion Lines'!$C:$C,'Completion Lines'!$G:$G,"Funding – Strensall remortgage advance (net)") -> 133528 | G6: Completion Lines
A7: 6 | B7: 17/07/2025 | C7: Funds from Alvine + money on account | D7: Director's loan – Alvine Tchega | E7: 0 | F7: =SUMIFS('Completion Lines'!$C:$C,'Completion Lines'!$G:$G,"Funding – Alvine Tchega")+SUMIFS('Completion Lines'!$C:$C,'Completion Lines'!$G:$G,"Funding – money on account") -> 18862.34 | G7: Completion Lines
A8: 7 | B8: 14/07/2025 | C8: Funds from Kakmeni towards purchase | D8: Loan – Kakmeni | E8: 0 | F8: =SUMIFS('Completion Lines'!$C:$C,'Completion Lines'!$G:$G,"Funding – Kakmeni") -> 38000 | G8: Completion Lines
A9: 8 | B9: Sep-25–Feb-26 | C9: Rent received – Kakmeni | D9: Cash at bank – Monzo | E9: =SUMIFS('Monzo Transactions'!$J:$J,'Monzo Transactions'!$G:$G,"Rent received – Kakmeni") -> 2200 | F9: 0 | G9: Monzo Transactions
A10: 9 | B10: Sep-25–Feb-26 | C10: Rent received – Kakmeni | D10: Rental income | E10: 0 | F10: =SUMIFS('Monzo Transactions'!$J:$J,'Monzo Transactions'!$G:$G,"Rent received – Kakmeni") -> 2200 | G10: Monzo Transactions
A11: 10 | B11: Sep-25–Feb-26 | C11: Other receipts (purpose not stated) | D11: Cash at bank – Monzo | E11: =SUMIFS('Monzo Transactions'!$J:$J,'Monzo Transactions'!$G:$G,"Other income received") -> 7132 | F11: 0 | G11: Monzo Transactions
A12: 11 | B12: Sep-25–Feb-26 | C12: Other receipts (purpose not stated) | D12: Other income (to confirm) | E12: 0 | F12: =SUMIFS('Monzo Transactions'!$J:$J,'Monzo Transactions'!$G:$G,"Other income received") -> 7132 | G12: Monzo Transactions
A13: 12 | B13: Dec-25–Jan-26 | C13: Building work – Alino Ltd | D13: Cash at bank – Monzo | E13: =SUMIFS('Monzo Transactions'!$J:$J,'Monzo Transactions'!$G:$G,"Building work income (Alino Ltd)") -> 4000 | F13: 0 | G13: Monzo Transactions
A14: 13 | B14: Dec-25–Jan-26 | C14: Building work – Alino Ltd | D14: Building work income | E14: 0 | F14: =SUMIFS('Monzo Transactions'!$J:$J,'Monzo Transactions'!$G:$G,"Building work income (Alino Ltd)") -> 4000 | G14: Monzo Transactions
A15: 14 | B15: Sep-25 | C15: Loans – The Kulture Bar | D15: Cash at bank – Monzo | E15: =SUMIFS('Monzo Transactions'!$J:$J,'Monzo Transactions'!$G:$G,"Loans received",'Monzo Transactions'!$D:$D,"THE KULTURE BAR AN") -> 6400 | F15: 0 | G15: Monzo Transactions
A16: 15 | B16: Sep-25 | C16: Loans – The Kulture Bar | D16: Loan – The Kulture Bar | E16: 0 | F16: =SUMIFS('Monzo Transactions'!$J:$J,'Monzo Transactions'!$G:$G,"Loans received",'Monzo Transactions'!$D:$D,"THE KULTURE BAR AN") -> 6400 | G16: Monzo Transactions
A17: 16 | B17: Feb-26 | C17: Loan – Kakmeni J | D17: Cash at bank – Monzo | E17: =SUMIFS('Monzo Transactions'!$J:$J,'Monzo Transactions'!$G:$G,"Loans received",'Monzo Transactions'!$D:$D,"KAKMENI J") -> 1000 | F17: 0 | G17: Monzo Transactions
A18: 17 | B18: Feb-26 | C18: Loan – Kakmeni J | D18: Loan – Kakmeni | E18: 0 | F18: =SUMIFS('Monzo Transactions'!$J:$J,'Monzo Transactions'!$G:$G,"Loans received",'Monzo Transactions'!$D:$D,"KAKMENI J") -> 1000 | G18: Monzo Transactions
A19: 18 | B19: Oct-25–Feb-26 | C19: Director transfers (net in) | D19: Cash at bank – Monzo | E19: =SUMIFS('Monzo Transactions'!$J:$J,'Monzo Transactions'!$G:$G,"Director transfers (Alvine Tchega)") -> 2600 | F19: 0 | G19: Monzo Transactions
A20: 19 | B20: Oct-25–Feb-26 | C20: Director transfers (net in) | D20: Director's loan – Alvine Tchega | E20: 0 | F20: =SUMIFS('Monzo Transactions'!$J:$J,'Monzo Transactions'!$G:$G,"Director transfers (Alvine Tchega)") -> 2600 | G20: Monzo Transactions
A21: 20 | B21: Sep-25–Oct-25 | C21: Seyat Can materials – capitalised (if switch = Asset) | D21: Property improvements – 36 Cairnsford Rd | E21: =IF(Notes!$B$10="Asset",-SUMIFS('Monzo Transactions'!$J:$J,'Monzo Transactions'!$G:$G,"Building materials (Seyat Can)"),0) -> 4500 | F21: 0 | G21: Monzo Transactions
A22: 21 | B22: Sep-25–Oct-25 | C22: Seyat Can materials – repairs (if switch = Repairs) | D22: Repairs & maintenance | E22: =IF(Notes!$B$10="Repairs",-SUMIFS('Monzo Transactions'!$J:$J,'Monzo Transactions'!$G:$G,"Building materials (Seyat Can)"),0) -> 0 | F22: 0 | G22: Monzo Transactions
A23: 22 | B23: Sep-25–Oct-25 | C23: Seyat Can materials paid | D23: Cash at bank – Monzo | E23: 0 | F23: =-SUMIFS('Monzo Transactions'!$J:$J,'Monzo Transactions'!$G:$G,"Building materials (Seyat Can)") -> 4500 | G23: Monzo Transactions
A24: 23 | B24: Oct-25 & Dec-25 | C24: Payments – Ahmed Sayyed / Alino Ltd | D24: Subcontractor / building costs | E24: =-SUMIFS('Monzo Transactions'!$J:$J,'Monzo Transactions'!$G:$G,"Payments to Alino / Ahmed Sayyed") -> 2200 | F24: 0 | G24: Monzo Transactions
A25: 24 | B25: Oct-25 & Dec-25 | C25: Payments – Ahmed Sayyed / Alino Ltd | D25: Cash at bank – Monzo | E25: 0 | F25: =-SUMIFS('Monzo Transactions'!$J:$J,'Monzo Transactions'!$G:$G,"Payments to Alino / Ahmed Sayyed") -> 2200 | G25: Monzo Transactions
A26: 25 | B26: Oct-25–Feb-26 | C26: Together Commercial direct debits | D26: Mortgage interest | E26: =-SUMIFS('Monzo Transactions'!$J:$J,'Monzo Transactions'!$G:$G,"Mortgage*") -> 16502.05 | F26: 0 | G26: Monzo Transactions
A27: 26 | B27: Oct-25–Feb-26 | C27: Together Commercial direct debits | D27: Cash at bank – Monzo | E27: 0 | F27: =-SUMIFS('Monzo Transactions'!$J:$J,'Monzo Transactions'!$G:$G,"Mortgage*") -> 16502.05 | G27: Monzo Transactions
A28: 27 | B28: Apr-25–Mar-26 | C28: Rent payable – 11 properties (if included) | D28: Rent payable | E28: =IF(Notes!$B$4="Yes",Notes!$B$5,0) -> 0 | F28: 0 | G28: Notes inputs / rent_split.xlsx
A29: 28 | B29: Aug-25 | C29: Goodlord payments (if included) | D29: Tenancy set-up costs (Goodlord) | E29: =IF(Notes!$B$4="Yes",Notes!$B$6,0) -> 0 | F29: 0 | G29: Notes inputs / rent_split.xlsx
A30: 29 | B30: Dec-25–Mar-26 | C30: IW Group Services (if included) | D30: Sundry expenses (IW Group Services) | E30: =IF(Notes!$B$4="Yes",Notes!$B$7,0) -> 0 | F30: 0 | G30: Notes inputs / rent_split.xlsx
A31: 30 | B31: Apr-25–Mar-26 | C31: Paid from other bank account – not provided | D31: Suspense – other bank account (not provided) | E31: 0 | F31: =IF(Notes!$B$4="Yes",Notes!$B$5+Notes!$B$6+Notes!$B$7,0) -> 0 | G31: Notes inputs / rent_split.xlsx
A32: 31 | B32: — | C32: Share capital (input) | D32: Cash at bank – share capital not traced | E32: =Notes!$B$8 -> 0 | F32: 0 | G32: Notes input
A33: 32 | B33: — | C33: Share capital (input) | D33: Share capital | E33: 0 | F33: =Notes!$B$8 -> 0 | G33: Notes input
A34: 33 | B34: — | C34: 30 Strensall Rd cost (input) | D34: Investment property – 30 Strensall Rd | E34: =Notes!$B$9 -> 0 | F34: 0 | G34: Notes input
A35: 34 | B35: — | C35: 30 Strensall Rd cost (input) | D35: Director's loan – Alvine Tchega | E35: 0 | F35: =Notes!$B$9 -> 0 | G35: Notes input – assumed introduced by director
D36: Totals | E36: =SUM(E2:E35) -> 548862.99 | F36: =SUM(F2:F35) -> 548862.99
D37: Debits − Credits (must be 0) | E37: =ROUND(E36-F36,2) -> 0

Sheet Monzo Reconciliation
A1: Monzo Business Account (Alino Property Ltd) – Monthly Reconciliation
A2: Blue = figures typed from the statement. Black = formulas from the Monzo Transactions sheet. Difference should be 0.
A4: Month | B4: Opening (£) | C4: Money In (£) | D4: Money Out (£) | E4: Calculated Closing (£) | F4: Statement Closing (£) | G4: Difference (£) | H4: Statement Deposits (£) | I4: Statement Outgoings (£) | J4: In / Out Check (£) | K4: Status | L4: Statement source
A5: 2025-09 | B5: 0 | C5: =SUMIFS('Monzo Transactions'!$H:$H,'Monzo Transactions'!$B:$B,$A5) -> 7682 | D5: =SUMIFS('Monzo Transactions'!$I:$I,'Monzo Transactions'!$B:$B,$A5) -> 3000 | E5: =B5+C5-D5 -> 4682 | F5: 4682 | G5: =ROUND(E5-F5,2) -> 0 | H5: 7682 | I5: 3000 | J5: =ROUND((C5-H5)+(D5-I5),2) -> 0 | K5: =IF(AND(G5=0,OR(J5=0,J5="n/a")),"Reconciled","CHECK") -> Reconciled | L5: PDF statement 01/09–30/09/2025
A6: 2025-10 | B6: =F5 -> 4682 | C6: =SUMIFS('Monzo Transactions'!$H:$H,'Monzo Transactions'!$B:$B,$A6) -> 5550 | D6: =SUMIFS('Monzo Transactions'!$I:$I,'Monzo Transactions'!$B:$B,$A6) -> 7800.41 | E6: =B6+C6-D6 -> 2431.59 | F6: 2431.59 | G6: =ROUND(E6-F6,2) -> 0 | H6: 5550 | I6: 7800.41 | J6: =ROUND((C6-H6)+(D6-I6),2) -> 0 | K6: =IF(AND(G6=0,OR(J6=0,J6="n/a")),"Reconciled","CHECK") -> Reconciled | L6: PDF statement 01/10–31/10/2025
A7: 2025-11 | B7: =F6 -> 2431.59 | C7: =SUMIFS('Monzo Transactions'!$H:$H,'Monzo Transactions'!$B:$B,$A7) -> 1000 | D7: =SUMIFS('Monzo Transactions'!$I:$I,'Monzo Transactions'!$B:$B,$A7) -> 3300.41 | E7: =B7+C7-D7 -> 131.18 | F7: 131.18 | G7: =ROUND(E7-F7,2) -> 0 | H7: 1000 | I7: 3300.41 | J7: =ROUND((C7-H7)+(D7-I7),2) -> 0 | K7: =IF(AND(G7=0,OR(J7=0,J7="n/a")),"Reconciled","CHECK") -> Reconciled | L7: PDF statement 01/11–30/11/2025
A8: 2025-12 | B8: =F7 -> 131.18 | C8: =SUMIFS('Monzo Transactions'!$H:$H,'Monzo Transactions'!$B:$B,$A8) -> 5300 | D8: =SUMIFS('Monzo Transactions'!$I:$I,'Monzo Transactions'!$B:$B,$A8) -> 3500.41 | E8: =B8+C8-D8 -> 1930.77 | F8: 1930.77 | G8: =ROUND(E8-F8,2) -> 0 | J8: n/a | K8: =IF(AND(G8=0,OR(J8=0,J8="n/a")),"Reconciled","CHECK") -> Reconciled | L8: Monzo export – last balance in month (no PDF)
A9: 2026-01 | B9: =F8 -> 1930.77 | C9: =SUMIFS('Monzo Transactions'!$H:$H,'Monzo Transactions'!$B:$B,$A9) -> 2400 | D9: =SUMIFS('Monzo Transactions'!$I:$I,'Monzo Transactions'!$B:$B,$A9) -> 3300.41 | E9: =B9+C9-D9 -> 1030.36 | F9: 1030.36 | G9: =ROUND(E9-F9,2) -> 0 | J9: n/a | K9: =IF(AND(G9=0,OR(J9=0,J9="n/a")),"Reconciled","CHECK") -> Reconciled | L9: Monzo export – last balance in month (no PDF)
A10: 2026-02 | B10: =F9 -> 1030.36 | C10: =SUMIFS('Monzo Transactions'!$H:$H,'Monzo Transactions'!$B:$B,$A10) -> 2400 | D10: =SUMIFS('Monzo Transactions'!$I:$I,'Monzo Transactions'!$B:$B,$A10) -> 3300.41 | E10: =B10+C10-D10 -> 129.95 | F10: 129.95 | G10: =ROUND(E10-F10,2) -> 0 | J10: n/a | K10: =IF(AND(G10=0,OR(J10=0,J10="n/a")),"Reconciled","CHECK") -> Reconciled | L10: Monzo export – last balance to 17/02/2026 (no PDF)
A11: Total | C11: =SUM(C5:C10) -> 24332 | D11: =SUM(D5:D10) -> 24202.05 | E11: =B5+C11-D11 -> 129.95 | F11: =F10 -> 129.95 | G11: =ROUND(E11-F11,2) -> 0
A13: Rows with a running-balance mismatch: | D13: =COUNTIF('Monzo Transactions'!M2:M37,"<>0") -> 0

Sheet Monzo Transactions
A1: Date | B1: Month | C1: Type | D1: Name | E1: Reference | F1: Monzo Category | G1: Category | H1: Money In (£) | I1: Money Out (£) | J1: Amount (£) | K1: Running Balance (£) | L1: Statement Balance (£) | M1: Difference (£) | N1: Source
A2: 45919 | B2: =TEXT(A2,"yyyy-mm") -> 2025-09 | C2: Faster payment | D2: THE KULTURE BAR AN | E2: loans | F2: Income | G2: Loans received | H2: =IF(J2>0,J2,0) -> 5000 | I2: =IF(J2<0,-J2,0) -> 0 | J2: 5000 | K2: =J2 -> 5000 | L2: 5000 | M2: =ROUND(K2-L2,2) -> 0 | N2: PDF statement Sep-2025
A3: 45919 | B3: =TEXT(A3,"yyyy-mm") -> 2025-09 | C3: Faster payment | D3: THE KULTURE BAR AN | E3: LOANS | F3: Income | G3: Loans received | H3: =IF(J3>0,J3,0) -> 1400 | I3: =IF(J3<0,-J3,0) -> 0 | J3: 1400 | K3: =K2+J3 -> 6400 | L3: 6400 | M3: =ROUND(K3-L3,2) -> 0 | N3: PDF statement Sep-2025
A4: 45921 | B4: =TEXT(A4,"yyyy-mm") -> 2025-09 | C4: Faster payment | D4: FRANCK ERIC NJIAGA | E4: CHASE | F4: Income | G4: Other income received | H4: =IF(J4>0,J4,0) -> 1282 | I4: =IF(J4<0,-J4,0) -> 0 | J4: 1282 | K4: =K3+J4 -> 7682 | L4: 7682 | M4: =ROUND(K4-L4,2) -> 0 | N4: PDF statement Sep-2025
A5: 45922 | B5: =TEXT(A5,"yyyy-mm") -> 2025-09 | C5: Faster payment | D5: Seyat Can | E5: Material | F5: Services | G5: Building materials (Seyat Can) | H5: =IF(J5>0,J5,0) -> 0 | I5: =IF(J5<0,-J5,0) -> 3000 | J5: -3000 | K5: =K4+J5 -> 4682 | L5: 4682 | M5: =ROUND(K5-L5,2) -> 0 | N5: PDF statement Sep-2025
A6: 45931 | B6: =TEXT(A6,"yyyy-mm") -> 2025-10 | C6: Faster payment | D6: Seyat Can | E6: Material | F6: Services | G6: Building materials (Seyat Can) | H6: =IF(J6>0,J6,0) -> 0 | I6: =IF(J6<0,-J6,0) -> 1500 | J6: -1500 | K6: =K5+J6 -> 3182 | L6: 3182 | M6: =ROUND(K6-L6,2) -> 0 | N6: Monzo export + PDF statement
A7: 45936 | B7: =TEXT(A7,"yyyy-mm") -> 2025-10 | C7: Faster payment | D7: FRANCK ERIC NJIAGA | E7: CHASE | F7: Income | G7: Other income received | H7: =IF(J7>0,J7,0) -> 1300 | I7: =IF(J7<0,-J7,0) -> 0 | J7: 1300 | K7: =K6+J7 -> 4482 | L7: 4482 | M7: =ROUND(K7-L7,2) -> 0 | N7: Monzo export + PDF statement
A8: 45936 | B8: =TEXT(A8,"yyyy-mm") -> 2025-10 | C8: Faster payment | D8: MIRABELLE SIEWE | E8: Mirabelle | F8: Income | G8: Other income received | H8: =IF(J8>0,J8,0) -> 1250 | I8: =IF(J8<0,-J8,0) -> 0 | J8: 1250 | K8: =K7+J8 -> 5732 | L8: 5732 | M8: =ROUND(K8-L8,2) -> 0 | N8: Monzo export + PDF statement
A9: 45936 | B9: =TEXT(A9,"yyyy-mm") -> 2025-10 | C9: Faster payment | D9: GUY NOEL DEUFI | E9: guy exch | F9: Income | G9: Other income received | H9: =IF(J9>0,J9,0) -> 500 | I9: =IF(J9<0,-J9,0) -> 0 | J9: 500 | K9: =K8+J9 -> 6232 | L9: 6232 | M9: =ROUND(K9-L9,2) -> 0 | N9: Monzo export + PDF statement
A10: 45937 | B10: =TEXT(A10,"yyyy-mm") -> 2025-10 | C10: Faster payment | D10: GUY NOEL DEUFI | E10: guy exch | F10: Income | G10: Other income received | H10: =IF(J10>0,J10,0) -> 2500 | I10: =IF(J10<0,-J10,0) -> 0 | J10: 2500 | K10: =K9+J10 -> 8732 | L10: 8732 | M10: =ROUND(K10-L10,2) -> 0 | N10: Monzo export + PDF statement
A11: 45944 | B11: =TEXT(A11,"yyyy-mm") -> 2025-10 | C11: Monzo-to-Monzo | D11: Alvine Tchega | E11: Alvine Tchega | F11: Transfers | G11: Director transfers (Alvine Tchega) | H11: =IF(J11>0,J11,0) -> 0 | I11: =IF(J11<0,-J11,0) -> 1000 | J11: -1000 | K11: =K10+J11 -> 7732 | L11: 7732 | M11: =ROUND(K11-L11,2) -> 0 | N11: Monzo export + PDF statement
A12: 45944 | B12: =TEXT(A12,"yyyy-mm") -> 2025-10 | C12: Faster payment | D12: Ahmed Sayyed | E12: Alino property Ltd | F12: Bills | G12: Payments to Alino / Ahmed Sayyed | H12: =IF(J12>0,J12,0) -> 0 | I12: =IF(J12<0,-J12,0) -> 2000 | J12: -2000 | K12: =K11+J12 -> 5732 | L12: 5732 | M12: =ROUND(K12-L12,2) -> 0 | N12: Monzo export + PDF statement
A13: 45947 | B13: =TEXT(A13,"yyyy-mm") -> 2025-10 | C13: Direct Debit | D13: Together Commercia | E13: 10395974-002 | F13: Bills | G13: Mortgage – Together Commercial (10395974-002) | H13: =IF(J13>0,J13,0) -> 0 | I13: =IF(J13<0,-J13,0) -> 2139.83 | J13: -2139.83 | K13: =K12+J13 -> 3592.17 | L13: 3592.17 | M13: =ROUND(K13-L13,2) -> 0 | N13: Monzo export + PDF statement
A14: 45947 | B14: =TEXT(A14,"yyyy-mm") -> 2025-10 | C14: Direct Debit | D14: Together Commercia | E14: 10395973-002 | F14: Bills | G14: Mortgage – Together Commercial (10395973-002) | H14: =IF(J14>0,J14,0) -> 0 | I14: =IF(J14<0,-J14,0) -> 1160.58 | J14: -1160.58 | K14: =K13+J14 -> 2431.59 | L14: 2431.59 | M14: =ROUND(K14-L14,2) -> 0 | N14: Monzo export + PDF statement
... A37: 46070 | B37: =TEXT(A37,"yyyy-mm") -> 2026-02 | C37: Direct Debit | D37: Together Commercia | E37: 10395974-002 | F37: Bills | G37: Mortgage – Together Commercial (10395974-002) | H37: =IF(J37>0,J37,0) -> 0 | I37: =IF(J37<0,-J37,0) -> 2139.83 | J37: -2139.83 | K37: =K36+J37 -> 129.95 | L37: 129.95 | M37: =ROUND(K37-L37,2) -> 0 | N37: Monzo export
G38: Total | H38: =SUM(H2:H37) -> 24332 | I38: =SUM(I2:I37) -> 24202.05 | J38: =SUM(J2:J37) -> 129.95

Sheet Monzo Categories
A1: Monzo – Totals by Category and Month (Amount: + in / − out)
A2: SUMIFS over the Monzo Transactions sheet. Change a Category there and this table follows.
A4: Category | B4: 2025-09 | C4: 2025-10 | D4: 2025-11 | E4: 2025-12 | F4: 2026-01 | G4: 2026-02 | H4: Total (£) | I4: Count | J4: Notes
A5: Building work income (Alino Ltd) | B5: =SUMIFS('Monzo Transactions'!$J:$J,'Monzo Transactions'!$G:$G,$A5,'Monzo Transactions'!$B:$B,B$4) -> 0 | C5: =SUMIFS('Monzo Transactions'!$J:$J,'Monzo Transactions'!$G:$G,$A5,'Monzo Transactions'!$B:$B,C$4) -> 0 | D5: =SUMIFS('Monzo Transactions'!$J:$J,'Monzo Transactions'!$G:$G,$A5,'Monzo Transactions'!$B:$B,D$4) -> 0 | E5: =SUMIFS('Monzo Transactions'!$J:$J,'Monzo Transactions'!$G:$G,$A5,'Monzo Transactions'!$B:$B,E$4) -> 2100 | F5: =SUMIFS('Monzo Transactions'!$J:$J,'Monzo Transactions'!$G:$G,$A5,'Monzo Transactions'!$B:$B,F$4) -> 1900 | G5: =SUMIFS('Monzo Transactions'!$J:$J,'Monzo Transactions'!$G:$G,$A5,'Monzo Transactions'!$B:$B,G$4) -> 0 | H5: =SUM(B5:G5) -> 4000 | I5: =COUNTIFS('Monzo Transactions'!$G:$G,$A5) -> 6
A6: Director transfers (Alvine Tchega) | B6: =SUMIFS('Monzo Transactions'!$J:$J,'Monzo Transactions'!$G:$G,$A6,'Monzo Transactions'!$B:$B,B$4) -> 0 | C6: =SUMIFS('Monzo Transactions'!$J:$J,'Monzo Transactions'!$G:$G,$A6,'Monzo Transactions'!$B:$B,C$4) -> -1000 | D6: =SUMIFS('Monzo Transactions'!$J:$J,'Monzo Transactions'!$G:$G,$A6,'Monzo Transactions'!$B:$B,D$4) -> 0 | E6: =SUMIFS('Monzo Transactions'!$J:$J,'Monzo Transactions'!$G:$G,$A6,'Monzo Transactions'!$B:$B,E$4) -> 2000 | F6: =SUMIFS('Monzo Transactions'!$J:$J,'Monzo Transactions'!$G:$G,$A6,'Monzo Transactions'!$B:$B,F$4) -> 200 | G6: =SUMIFS('Monzo Transactions'!$J:$J,'Monzo Transactions'!$G:$G,$A6,'Monzo Transactions'!$B:$B,G$4) -> 1400 | H6: =SUM(B6:G6) -> 2600 | I6: =COUNTIFS('Monzo Transactions'!$G:$G,$A6) -> 4 | J6: Account holder moving own money in/out.
A7: Loans received | B7: =SUMIFS('Monzo Transactions'!$J:$J,'Monzo Transactions'!$G:$G,$A7,'Monzo Transactions'!$B:$B,B$4) -> 6400 | C7: =SUMIFS('Monzo Transactions'!$J:$J,'Monzo Transactions'!$G:$G,$A7,'Monzo Transactions'!$B:$B,C$4) -> 0 | D7: =SUMIFS('Monzo Transactions'!$J:$J,'Monzo Transactions'!$G:$G,$A7,'Monzo Transactions'!$B:$B,D$4) -> 0 | E7: =SUMIFS('Monzo Transactions'!$J:$J,'Monzo Transactions'!$G:$G,$A7,'Monzo Transactions'!$B:$B,E$4) -> 0 | F7: =SUMIFS('Monzo Transactions'!$J:$J,'Monzo Transactions'!$G:$G,$A7,'Monzo Transactions'!$B:$B,F$4) -> 0 | G7: =SUMIFS('Monzo Transactions'!$J:$J,'Monzo Transactions'!$G:$G,$A7,'Monzo Transactions'!$B:$B,G$4) -> 1000 | H7: =SUM(B7:G7) -> 7400 | I7: =COUNTIFS('Monzo Transactions'!$G:$G,$A7) -> 3 | J7: Kulture Bar 'loans' (Sep) and Kakmeni J 'Loan' (Feb).
A8: Other income received | B8: =SUMIFS('Monzo Transactions'!$J:$J,'Monzo Transactions'!$G:$G,$A8,'Monzo Transactions'!$B:$B,B$4) -> 1282 | C8: =SUMIFS('Monzo Transactions'!$J:$J,'Monzo Transactions'!$G:$G,$A8,'Monzo Transactions'!$B:$B,C$4) -> 5550 | D8: =SUMIFS('Monzo Transactions'!$J:$J,'Monzo Transactions'!$G:$G,$A8,'Monzo Transactions'!$B:$B,D$4) -> 0 | E8: =SUMIFS('Monzo Transactions'!$J:$J,'Monzo Transactions'!$G:$G,$A8,'Monzo Transactions'!$B:$B,E$4) -> 0 | F8: =SUMIFS('Monzo Transactions'!$J:$J,'Monzo Transactions'!$G:$G,$A8,'Monzo Transactions'!$B:$B,F$4) -> 300 | G8: =SUMIFS('Monzo Transactions'!$J:$J,'Monzo Transactions'!$G:$G,$A8,'Monzo Transactions'!$B:$B,G$4) -> 0 | H8: =SUM(B8:G8) -> 7132 | I8: =COUNTIFS('Monzo Transactions'!$G:$G,$A8) -> 6 | J8: Njiaga (CHASE), Siewe, Deufi (guy exch), Kouchoufondjo – purpose not stated; confirm.
A9: Rent received – Kakmeni | B9: =SUMIFS('Monzo Transactions'!$J:$J,'Monzo Transactions'!$G:$G,$A9,'Monzo Transactions'!$B:$B,B$4) -> 0 | C9: =SUMIFS('Monzo Transactions'!$J:$J,'Monzo Transactions'!$G:$G,$A9,'Monzo Transactions'!$B:$B,C$4) -> 0 | D9: =SUMIFS('Monzo Transactions'!$J:$J,'Monzo Transactions'!$G:$G,$A9,'Monzo Transactions'!$B:$B,D$4) -> 1000 | E9: =SUMIFS('Monzo Transactions'!$J:$J,'Monzo Transactions'!$G:$G,$A9,'Monzo Transactions'!$B:$B,E$4) -> 1200 | F9: =SUMIFS('Monzo Transactions'!$J:$J,'Monzo Transactions'!$G:$G,$A9,'Monzo Transactions'!$B:$B,F$4) -> 0 | G9: =SUMIFS('Monzo Transactions'!$J:$J,'Monzo Transactions'!$G:$G,$A9,'Monzo Transactions'!$B:$B,G$4) -> 0 | H9: =SUM(B9:G9) -> 2200 | I9: =COUNTIFS('Monzo Transactions'!$G:$G,$A9) -> 3 | J9: Assumed rent: one payment says 'Rent'; Revolut payments from the same person treated the same. 'Loan' payment is under Loans received.
A10: Building materials (Seyat Can) | B10: =SUMIFS('Monzo Transactions'!$J:$J,'Monzo Transactions'!$G:$G,$A10,'Monzo Transactions'!$B:$B,B$4) -> -3000 | C10: =SUMIFS('Monzo Transactions'!$J:$J,'Monzo Transactions'!$G:$G,$A10,'Monzo Transactions'!$B:$B,C$4) -> -1500 | D10: =SUMIFS('Monzo Transactions'!$J:$J,'Monzo Transactions'!$G:$G,$A10,'Monzo Transactions'!$B:$B,D$4) -> 0 | E10: =SUMIFS('Monzo Transactions'!$J:$J,'Monzo Transactions'!$G:$G,$A10,'Monzo Transactions'!$B:$B,E$4) -> 0 | F10: =SUMIFS('Monzo Transactions'!$J:$J,'Monzo Transactions'!$G:$G,$A10,'Monzo Transactions'!$B:$B,F$4) -> 0 | G10: =SUMIFS('Monzo Transactions'!$J:$J,'Monzo Transactions'!$G:$G,$A10,'Monzo Transactions'!$B:$B,G$4) -> 0 | H10: =SUM(B10:G10) -> -4500 | I10: =COUNTIFS('Monzo Transactions'!$G:$G,$A10) -> 2
A11: Mortgage – Together Commercial (10395973-002) | B11: =SUMIFS('Monzo Transactions'!$J:$J,'Monzo Transactions'!$G:$G,$A11,'Monzo Transactions'!$B:$B,B$4) -> 0 | C11: =SUMIFS('Monzo Transactions'!$J:$J,'Monzo Transactions'!$G:$G,$A11,'Monzo Transactions'!$B:$B,C$4) -> -1160.58 | D11: =SUMIFS('Monzo Transactions'!$J:$J,'Monzo Transactions'!$G:$G,$A11,'Monzo Transactions'!$B:$B,D$4) -> -1160.58 | E11: =SUMIFS('Monzo Transactions'!$J:$J,'Monzo Transactions'!$G:$G,$A11,'Monzo Transactions'!$B:$B,E$4) -> -1160.58 | F11: =SUMIFS('Monzo Transactions'!$J:$J,'Monzo Transactions'!$G:$G,$A11,'Monzo Transactions'!$B:$B,F$4) -> -1160.58 | G11: =SUMIFS('Monzo Transactions'!$J:$J,'Monzo Transactions'!$G:$G,$A11,'Monzo Transactions'!$B:$B,G$4) -> -1160.58 | H11: =SUM(B11:G11) -> -5802.9 | I11: =COUNTIFS('Monzo Transactions'!$G:$G,$A11) -> 5
A12: Mortgage – Together Commercial (10395974-002) | B12: =SUMIFS('Monzo Transactions'!$J:$J,'Monzo Transactions'!$G:$G,$A12,'Monzo Transactions'!$B:$B,B$4) -> 0 | C12: =SUMIFS('Monzo Transactions'!$J:$J,'Monzo Transactions'!$G:$G,$A12,'Monzo Transactions'!$B:$B,C$4) -> -2139.83 | D12: =SUMIFS('Monzo Transactions'!$J:$J,'Monzo Transactions'!$G:$G,$A12,'Monzo Transactions'!$B:$B,D$4) -> -2139.83 | E12: =SUMIFS('Monzo Transactions'!$J:$J,'Monzo Transactions'!$G:$G,$A12,'Monzo Transactions'!$B:$B,E$4) -> -2139.83 | F12: =SUMIFS('Monzo Transactions'!$J:$J,'Monzo Transactions'!$G:$G,$A12,'Monzo Transactions'!$B:$B,F$4) -> -2139.83 | G12: =SUMIFS('Monzo Transactions'!$J:$J,'Monzo Transactions'!$G:$G,$A12,'Monzo Transactions'!$B:$B,G$4) -> -2139.83 | H12: =SUM(B12:G12) -> -10699.15 | I12: =COUNTIFS('Monzo Transactions'!$G:$G,$A12) -> 5
A13: Payments to Alino / Ahmed Sayyed | B13: =SUMIFS('Monzo Transactions'!$J:$J,'Monzo Transactions'!$G:$G,$A13,'Monzo Transactions'!$B:$B,B$4) -> 0 | C13: =SUMIFS('Monzo Transactions'!$J:$J,'Monzo Transactions'!$G:$G,$A13,'Monzo Transactions'!$B:$B,C$4) -> -2000 | D13: =SUMIFS('Monzo Transactions'!$J:$J,'Monzo Transactions'!$G:$G,$A13,'Monzo Transactions'!$B:$B,D$4) -> 0 | E13: =SUMIFS('Monzo Transactions'!$J:$J,'Monzo Transactions'!$G:$G,$A13,'Monzo Transactions'!$B:$B,E$4) -> -200 | F13: =SUMIFS('Monzo Transactions'!$J:$J,'Monzo Transactions'!$G:$G,$A13,'Monzo Transactions'!$B:$B,F$4) -> 0 | G13: =SUMIFS('Monzo Transactions'!$J:$J,'Monzo Transactions'!$G:$G,$A13,'Monzo Transactions'!$B:$B,G$4) -> 0 | H13: =SUM(B13:G13) -> -2200 | I13: =COUNTIFS('Monzo Transactions'!$G:$G,$A13) -> 2 | J13: Ahmed Sayyed payment had reference 'Alino property Ltd'.
A14: Net movement | B14: =SUM(B5:B13) -> 4682 | C14: =SUM(C5:C13) -> -2250.41 | D14: =SUM(D5:D13) -> -2300.41 | E14: =SUM(E5:E13) -> 1799.59 | F14: =SUM(F5:F13) -> -900.41 | G14: =SUM(G5:G13) -> -900.41 | H14: =SUM(H5:H13) -> 129.95 | I14: =SUM(I5:I13) -> 36
A15: Check vs reconciliation (should be 0) | B15: =ROUND(B14-('Monzo Reconciliation'!C5-'Monzo Reconciliation'!D5),2) -> 0 | C15: =ROUND(C14-('Monzo Reconciliation'!C6-'Monzo Reconciliation'!D6),2) -> 0 | D15: =ROUND(D14-('Monzo Reconciliation'!C7-'Monzo Reconciliation'!D7),2) -> 0 | E15: =ROUND(E14-('Monzo Reconciliation'!C8-'Monzo Reconciliation'!D8),2) -> 0 | F15: =ROUND(F14-('Monzo Reconciliation'!C9-'Monzo Reconciliation'!D9),2) -> 0 | G15: =ROUND(G14-('Monzo Reconciliation'!C10-'Monzo Reconciliation'!D10),2) -> 0

Sheet Completion Lines
A1: Statement | B1: Item | C1: Paid In (£) | D1: Paid Out – net (£) | E1: VAT (£) | F1: Paid Out – gross (£) | G1: Classification
A2: 30 Strensall Rd – Remortgage (17/07/2025) | B2: Mortgage advance minus 3rd party solicitors fee | C2: 133528 | D2: 0 | E2: 0 | F2: =D2+E2 -> 0 | G2: Funding – Strensall remortgage advance (net)
A3: 30 Strensall Rd – Remortgage (17/07/2025) | B3: Money on account 8.4.2025 | C3: 100 | D3: 0 | E3: 0 | F3: =D3+E3 -> 0 | G3: Funding – money on account
A4: 30 Strensall Rd – Remortgage (17/07/2025) | B4: Legal Fees | C4: 0 | D4: 650 | E4: 130 | F4: =D4+E4 -> 780 | G4: Finance cost – Strensall remortgage
A5: 30 Strensall Rd – Remortgage (17/07/2025) | B5: File Setup Fee | C5: 0 | D5: 35 | E5: 7 | F5: =D5+E5 -> 42 | G5: Finance cost – Strensall remortgage
A6: 30 Strensall Rd – Remortgage (17/07/2025) | B6: Mortgage Fee | C6: 0 | D6: 200 | E6: 40 | F6: =D6+E6 -> 240 | G6: Finance cost – Strensall remortgage
A7: 30 Strensall Rd – Remortgage (17/07/2025) | B7: Third party sols fee for dealing | C7: 0 | D7: 300 | E7: 60 | F7: =D7+E7 -> 360 | G7: Finance cost – Strensall remortgage
A8: 30 Strensall Rd – Remortgage (17/07/2025) | B8: No Searches Indemnity Insurance Policy | C8: 0 | D8: 29 | E8: 0 | F8: =D8+E8 -> 29 | G8: Finance cost – Strensall remortgage
A9: 30 Strensall Rd – Remortgage (17/07/2025) | B9: Land Charges Search (£6 per person) x 3 | C9: 0 | D9: 18 | E9: 0 | F9: =D9+E9 -> 18 | G9: Finance cost – Strensall remortgage
A10: 30 Strensall Rd – Remortgage (17/07/2025) | B10: Bank Transfer Fee | C10: 0 | D10: 45 | E10: 0 | F10: =D10+E10 -> 45 | G10: Finance cost – Strensall remortgage
A11: 30 Strensall Rd – Remortgage (17/07/2025) | B11: Land Registry Documents | C11: 0 | D11: 14 | E11: 0 | F11: =D11+E11 -> 14 | G11: Finance cost – Strensall remortgage
A12: 30 Strensall Rd – Remortgage (17/07/2025) | B12: Land Registry Search – OS1 | C12: 0 | D12: 7 | E12: 0 | F12: =D12+E12 -> 7 | G12: Finance cost – Strensall remortgage
A13: 30 Strensall Rd – Remortgage (17/07/2025) | B13: Land Registry Fees | C13: 0 | D13: 45 | E13: 0 | F13: =D13+E13 -> 45 | G13: Finance cost – Strensall remortgage
... A41: 36 Cairnsford Rd – Purchase (17/07/2025) | B41: Insolvency indemnity policy required by lender | C41: 0 | D41: 160 | E41: 0 | F41: =D41+E41 -> 160 | G41: Finance cost – Cairnsford mortgage
A43: Check against statement totals
A44: Statement | C44: Paid In – calc | D44: Paid In – statement | E44: Paid Out – calc | F44: Paid Out – statement | G44: Status
A45: 30 Strensall Rd – Remortgage (17/07/2025) | B45: PDF: CompletionStatement_1093081_Tchega_2025-07-15 (total out £1,670 + balance due £131,958) | C45: =SUMIFS($C$2:$C$41,$A$2:$A$41,$A45) -> 133628 | D45: 133628 | E45: =SUMIFS($F$2:$F$41,$A$2:$A$41,$A45) -> 133628 | F45: 133628 | G45: =IF(AND(ROUND(C45-D45,2)=0,ROUND(E45-F45,2)=0,ROUND(C45-E45,2)=0),"Agrees – balances to £0","CHECK") -> Agrees – balances to £0
A46: 36 Cairnsford Rd – Purchase (17/07/2025) | B46: PDF: Complation_Statement (DWS Legal), totals £500,658.94 / £500,658.94, balance £0.00 | C46: =SUMIFS($C$2:$C$41,$A$2:$A$41,$A46) -> 500658.94 | D46: 500658.94 | E46: =SUMIFS($F$2:$F$41,$A$2:$A$41,$A46) -> 500658.94 | F46: 500658.94 | G46: =IF(AND(ROUND(C46-D46,2)=0,ROUND(E46-F46,2)=0,ROUND(C46-E46,2)=0),"Agrees – balances to £0","CHECK") -> Agrees – balances to £0

Sheet Property Purchase
A1: 36 Cairnsford Road, Leicester LE2 6GF – Purchase Analysis (Alino Property Ltd)
A2: Completed 17/07/2025, funded partly by remortgage of 30 Strensall Road. All figures are SUMIFS over Completion Lines (gross incl. VAT – treated as irrecoverable).
A4: A. Cost of property (capitalise – fixed asset / investment property) | B4: £ | C4: Notes
A5: Purchase price | B5: =SUMIFS('Completion Lines'!$F$2:$F$41,'Completion Lines'!$G$2:$G$41,"Property cost – purchase price") -> 462000
A6: Stamp Duty Land Tax | B6: =SUMIFS('Completion Lines'!$F$2:$F$41,'Completion Lines'!$G$2:$G$41,"Property cost – Stamp Duty (SDLT)") -> 36200 | C6: SDLT is part of the cost of the property
A7: Legal & acquisition fees (incl. VAT) | B7: =SUMIFS('Completion Lines'!$F$2:$F$41,'Completion Lines'!$G$2:$G$41,"Property cost – legal & acquisition fees") -> 1743.94 | C7: Legal, searches, Land Registry, AML, SDLT form, bank transfer
A8: Total cost of 36 Cairnsford Road | B8: =SUM(B5:B7) -> 499943.94
A10: B. Finance / loan arrangement costs (not property cost) | B10: £ | C10: Notes
A11: Cairnsford mortgage – lender-related fees | B11: =SUMIFS('Completion Lines'!$F$2:$F$41,'Completion Lines'!$G$2:$G$41,"Finance cost – Cairnsford mortgage") -> 715 | C11: Mortgage admin, lender sols, policy arrangement, insolvency indemnity, MR01
A12: 30 Strensall remortgage – all costs | B12: =SUMIFS('Completion Lines'!$F$2:$F$41,'Completion Lines'!$G$2:$G$41,"Finance cost – Strensall remortgage") -> 1670 | C12: Whole remortgage statement (£1,670); spread over loan term or expense
A13: Total finance costs | B13: =SUM(B11:B12) -> 2385
A15: C. How the purchase was funded (Cairnsford statement – paid in) | B15: £ | C15: Notes
A16: Together Commercial mortgage (net advance) | B16: =SUMIFS('Completion Lines'!$C$2:$C$41,'Completion Lines'!$G$2:$G$41,"Funding – Together Commercial mortgage (net)") -> 311938.6 | C16: Net of lender's solicitor fees; gross loan not shown on statement
A17: Proceeds of 30 Strensall remortgage | B17: =SUMIFS('Completion Lines'!$C$2:$C$41,'Completion Lines'!$G$2:$G$41,"Transfer – Strensall proceeds to Cairnsford",'Completion Lines'!$A$2:$A$41,"36 Cairnsford Rd – Purchase (17/07/2025)") -> 131958 | C17: Equals £133,528 advance + £100 on account − £1,670 costs
A18: Alvine Tchega – money in 14/07/2025 | B18: =SUMIFS('Completion Lines'!$C$2:$C$41,'Completion Lines'!$G$2:$G$41,"Funding – Alvine Tchega") -> 18362.34 | C18: Director's loan to company (confirm)
A19: Kakmeni – money in 14/07/2025 | B19: =SUMIFS('Completion Lines'!$C$2:$C$41,'Completion Lines'!$G$2:$G$41,"Funding – Kakmeni") -> 38000 | C19: Loan or investment? Ties to Kakmeni receipts on Monzo (confirm)
A20: Money on account (Cairnsford) | B20: =SUMIFS('Completion Lines'!$C$2:$C$41,'Completion Lines'!$G$2:$G$41,"Funding – money on account",'Completion Lines'!$A$2:$A$41,"36 Cairnsford Rd – Purchase (17/07/2025)") -> 400
A21: Total funds in for purchase | B21: =SUM(B16:B20) -> 500658.94
A23: D. Check | B23: £ | C23: Notes
A24: Cost (A) + Cairnsford finance fees | B24: =B8+B11 -> 500658.94
A25: Funds in (C) | B25: =B21 -> 500658.94
A26: Difference (should be 0) | B26: =ROUND(B24-B25,2) -> 0
A28: E. Ongoing mortgage payments (from Monzo business account) | B28: £ | C28: Notes
A29: Together Commercial DD 10395974-002 – paid Oct-25 to Feb-26 | B29: =-SUMIFS('Monzo Transactions'!$J:$J,'Monzo Transactions'!$E:$E,"10395974-002") -> 10699.15 | C29: Likely the larger Cairnsford loan (confirm with Together)
A30: Together Commercial DD 10395973-002 – paid Oct-25 to Feb-26 | B30: =-SUMIFS('Monzo Transactions'!$J:$J,'Monzo Transactions'!$E:$E,"10395973-002") -> 5802.9 | C30: Likely the 30 Strensall remortgage (confirm with Together)
