Workbook

Sheet JV-001 Property Purchase
A1: Alino Property Ltd
A2: Journal Voucher
A4: JV No. | B4: JV-001
A5: Date | B5: 17/07/2025
A6: Narration | B6: Purchase of 36 Cairnsford Road, Leicester LE2 6GF, funded by a Together Commercial mortgage, the remortgage of 30 Strensall Road, and funds from Alvine Tchega and Kakmeni (per both completion statements).
A8: Line | B8: Account | C8: Description | D8: Debit (£) | E8: Credit (£) | F8: Source
A9: 1 | B9: Investment property – 36 Cairnsford Rd | C9: Purchase price | D9: ='Cairnsford Purchase'!E8 -> 462000 | F9: Cairnsford: Purchase Price
A10: 2 | B10: Investment property – 36 Cairnsford Rd | C10: Stamp Duty Land Tax | D10: ='Cairnsford Purchase'!E26 -> 36200 | F10: Cairnsford: Stamp Duty (SDLT)
A11: 3 | B11: Investment property – 36 Cairnsford Rd | C11: Legal & acquisition fees incl. VAT (12 items) | D11: ='Cairnsford Purchase'!E14+'Cairnsford Purchase'!E16+'Cairnsford Purchase'!E17+'Cairnsford Purchase'!E18+'Cairnsford Purchase'!E21+'Cairnsford Purchase'!E22+'Cairnsford Purchase'!E23+'Cairnsford Purchase'!E24+'Cairnsford Purchase'!E25+'Cairnsford Purchase'!E27+'Cairnsford Purchase'!E28+'Cairnsford Purchase'!E30 -> 1743.94 | F11: Cairnsford: legal, searches, LR, AML, SDLT form, bank fee
A12: 4 | B12: Loan arrangement fees | C12: Lender-related fees – Cairnsford mortgage, incl. VAT | D12: ='Cairnsford Purchase'!E15+'Cairnsford Purchase'!E19+'Cairnsford Purchase'!E20+'Cairnsford Purchase'!E29+'Cairnsford Purchase'!E31 -> 715 | F12: Cairnsford: mortgage admin, lender sols, policy, MR01, insolvency indemnity
A13: 5 | B13: Loan arrangement fees | C13: Remortgage costs – 30 Strensall Rd, incl. VAT | D13: ='Strensall Remortgage'!E10+'Strensall Remortgage'!E11+'Strensall Remortgage'!E12+'Strensall Remortgage'!E13+'Strensall Remortgage'!E14+'Strensall Remortgage'!E15+'Strensall Remortgage'!E16+'Strensall Remortgage'!E17+'Strensall Remortgage'!E18+'Strensall Remortgage'!E19+'Strensall Remortgage'!E20+'Strensall Remortgage'!E21+'Strensall Remortgage'!E22 -> 1670 | F13: Strensall: all 13 fee lines
A14: 6 | B14: Mortgage – Together Commercial (Cairnsford) | C14: Net mortgage advance – 36 Cairnsford Rd | E14: ='Cairnsford Purchase'!B10 -> 311938.6 | F14: Cairnsford: Mortgage advance
A15: 7 | B15: Mortgage – Together Commercial (Strensall) | C15: Net remortgage advance – 30 Strensall Rd | E15: ='Strensall Remortgage'!B8 -> 133528 | F15: Strensall: Mortgage advance
A16: 8 | B16: Director's loan – Alvine Tchega | C16: Funds introduced 14/07/2025 | E16: ='Cairnsford Purchase'!B12 -> 18362.34 | F16: Cairnsford: Money from client – Alvine
A17: 9 | B17: Director's loan – Alvine Tchega | C17: Money on account paid to solicitors (£400 + £100) | E17: ='Cairnsford Purchase'!B9+'Strensall Remortgage'!B9 -> 500 | F17: Both: Money on account
A18: 10 | B18: Loan – Kakmeni | C18: Funds introduced 14/07/2025 | E18: ='Cairnsford Purchase'!B13 -> 38000 | F18: Cairnsford: Money from client – Kakmeni
C19: Totals | D19: =SUM(D9:D18) -> 502328.94 | E19: =SUM(E9:E18) -> 502328.94
C20: Difference (must be 0) | D20: =ROUND(D19-E19,2) -> 0 | E20: =IF(D20=0,"Balanced","NOT BALANCED") -> Balanced
A22: Notes
A23: 1. Green figures are formulas linked to the line items on the two statement sheets in this workbook.
A24: 2. The 30 Strensall balance of £131,958.00 was paid out on the Strensall statement and received on the Cairnsford statement. It nets to nil, so it is not posted.
A25: 3. Total cost of 36 Cairnsford Rd = lines 1–3. VAT on fees is included because the company is assumed not to be VAT-registered.
A26: 4. Lender and remortgage fees (lines 4–5) are posted to Loan arrangement fees (P&L finance cost). Under FRS 102 they can instead be netted against the loans and spread over the loan term.
A27: 5. Mortgages are recorded at the net advance shown on the statements. The gross loans per the Together Commercial offers may be higher by the lender's solicitor fees.
A28: 6. Alvine's funds are treated as the director's loan account and Kakmeni's £38,000 as a loan. Change these if they were share capital or another arrangement.
A30: Prepared by:
A31: Reviewed by:
A32: Posted (date):

Sheet Strensall Remortgage
A1: Completion Statement
A2: Completion (17/07/2025)
A3: Alvine Nadege Kouaya Tchega (1093081)
A4: Remortgage of 30 Strensall Road, Leicester, LE2 9FT
A7: Item | B7: Paid In (£) | C7: Paid Out (£) | D7: VAT (£) | E7: Paid Out incl. VAT (£)
A8: Mortgage advance minus 3rd party solicitors fee | B8: 133528
A9: Money on account 8.4.2025 | B9: 100
A10: Legal Fees | C10: 650 | D10: 130 | E10: =C10+D10 -> 780
A11: File Setup Fee | C11: 35 | D11: 7 | E11: =C11+D11 -> 42
A12: Mortgage Fee | C12: 200 | D12: 40 | E12: =C12+D12 -> 240
A13: Third party sols fee for dealing | C13: 300 | D13: 60 | E13: =C13+D13 -> 360
A14: No Searches Indemnity Insurance Policy | C14: 29 | E14: =C14+D14 -> 29
A15: Land Charges Search (£6 per person) x 3 | C15: 18 | E15: =C15+D15 -> 18
A16: Bank Transfer Fee | C16: 45 | E16: =C16+D16 -> 45
A17: Land Registry Documents | C17: 14 | E17: =C17+D17 -> 14
A18: Land Registry Search – OS1 | C18: 7 | E18: =C18+D18 -> 7
A19: Land Registry Fees | C19: 45 | E19: =C19+D19 -> 45
A20: MR01 Companies House registration of charge | C20: 15 | E20: =C20+D20 -> 15
A21: Company winding up search | C21: 15 | E21: =C21+D21 -> 15
A22: Company search – Global | C22: 60 | E22: =C22+D22 -> 60
A23: Total | B23: =SUM(B8:B22) -> 133628 | C23: =SUM(C8:C22) -> 1433 | D23: =SUM(D8:D22) -> 237 | E23: =SUM(E8:E22) -> 1670
A25: Balance due to you on completion | E25: =B23-E23 -> 131958
A27: Check against PDF statement
A28: Total paid in per statement | B28: 133628 | C28: =IF(ROUND(B23-B28,2)=0,"Agrees","DIFFERENCE "&TEXT(B23-B28,"#,##0.00")) -> Agrees
A29: Total paid out per statement (incl. VAT) | B29: 1670 | C29: =IF(ROUND(E23-B29,2)=0,"Agrees","DIFFERENCE "&TEXT(E23-B29,"#,##0.00")) -> Agrees
A30: Balance due per statement | B30: 131958 | C30: =IF(ROUND(E25-B30,2)=0,"Agrees","DIFFERENCE "&TEXT(E25-B30,"#,##0.00")) -> Agrees
A32: The £131,958.00 balance was paid into the 36 Cairnsford Road purchase (see 'Cairnsford Purchase' sheet: 'Proceeds from 30 Strensall').
A33: Blue = typed from the PDF statement; black = formulas.

Sheet Cairnsford Purchase
A1: Completion Statement – DWS Legal
A2: Exchange (17/07/2025) Completion (17/07/2025)
A3: Alino Property Limited
A4: Purchase of 36 Cairnsford Road, Leicester, LE2 6GF
A5: Mortgage provided by: Together Commercial Finance Limited c/o Priority Law Solicitors
A7: Item | B7: Paid In (£) | C7: Paid Out (£) | D7: VAT (£) | E7: Paid Out incl. VAT (£)
A8: Purchase Price | C8: 462000 | E8: =C8+D8 -> 462000
A9: Money on Account | B9: 400
A10: Mortgage advance from lender's solicitors (net of their fees) | B10: 311938.6
A11: Proceeds from 30 Strensall | B11: 131958
A12: Money from client – Alvine 14.7.25 | B12: 18362.34
A13: Money from client – Kakmeni 14.7.25 | B13: 38000
A14: Legal Fees | C14: 775 | D14: 155 | E14: =C14+D14 -> 930
A15: Mortgage Admin Fee | C15: 100 | D15: 20 | E15: =C15+D15 -> 120
A16: File Setup Fee | C16: 35 | D16: 7 | E16: =C16+D16 -> 42
A17: Stamp Duty Land Tax Form Fee | C17: 75 | D17: 15 | E17: =C17+D17 -> 90
A18: Anti-Money Laundering Check Fee (£30 pp) | C18: 60 | D18: 12 | E18: =C18+D18 -> 72
A19: Third party lender solicitors fee | C19: 300 | D19: 60 | E19: =C19+D19 -> 360
A20: Policy arrangement fee | C20: 50 | D20: 10 | E20: =C20+D20 -> 60
A21: Land Registry Search | C21: 7 | E21: =C21+D21 -> 7
A22: Land Charges Search (£6 pp) | C22: 18 | E22: =C22+D22 -> 18
A23: Bank Transfer Fee | C23: 45 | E23: =C23+D23 -> 45
A24: Searches Pack | C24: 109.66 | E24: =C24+D24 -> 109.66
A25: Land Registry Fees | C25: 150 | E25: =C25+D25 -> 150
A26: Stamp Duty (SDLT) | C26: 36200 | E26: =C26+D26 -> 36200
A27: Search perusal Fee | C27: 200.28 | E27: =C27+D27 -> 200.28
A28: Company search fee | C28: 60 | E28: =C28+D28 -> 60
A29: MR01 | C29: 15 | E29: =C29+D29 -> 15
A30: Winding up Search Fee | C30: 20 | E30: =C30+D30 -> 20
A31: Insolvency indemnity policy required by lender | C31: 160 | E31: =C31+D31 -> 160
A32: Total | B32: =SUM(B8:B31) -> 500658.94 | C32: =SUM(C8:C31) -> 500379.94 | D32: =SUM(D8:D31) -> 279 | E32: =SUM(E8:E31) -> 500658.94
A34: Balance due to you on completion | E34: =B32-E32 -> 0
A36: Check against PDF statement
A37: Total paid in per statement | B37: 500658.94 | C37: =IF(ROUND(B32-B37,2)=0,"Agrees","DIFFERENCE "&TEXT(B32-B37,"#,##0.00")) -> Agrees
A38: Total paid out per statement (incl. VAT) | B38: 500658.94 | C38: =IF(ROUND(E32-B38,2)=0,"Agrees","DIFFERENCE "&TEXT(E32-B38,"#,##0.00")) -> Agrees
A39: Balance due per statement | B39: 0 | C39: =IF(ROUND(E34-B39,2)=0,"Agrees","DIFFERENCE "&TEXT(E34-B39,"#,##0.00")) -> Agrees
A41: 'Proceeds from 30 Strensall' £131,958.00 = balance due on the Strensall remortgage statement.
A42: Blue = typed from the PDF statement; black = formulas.
