Workbook

Sheet Monzo Reconciliation
A1: Monzo Business Account (Alino Property Ltd) – Monthly Reconciliation
A2: Blue = figures typed from the statement. Black = formulas from the Monzo Transactions sheet. Difference should be 0.
A4: Month | B4: Opening (£) | C4: Money In (£) | D4: Money Out (£) | E4: Calculated Closing (£) | F4: Statement Closing (£) | G4: Difference (£) | H4: Statement Deposits (£) | I4: Statement Outgoings (£) | J4: In / Out Check (£) | K4: Status | L4: Statement source
A5: 2025-09 | B5: 0 | C5: =SUMIFS('Monzo Transactions'!$H:$H,'Monzo Transactions'!$B:$B,$A5) -> 7682 | D5: =SUMIFS('Monzo Transactions'!$I:$I,'Monzo Transactions'!$B:$B,$A5) -> 3000 | E5: =B5+C5-D5 -> 4682 | F5: 4682 | G5: =ROUND(E5-F5,2) -> 0 | H5: 7682 | I5: 3000 | J5: =ROUND((C5-H5)+(D5-I5),2) -> 0 | K5: =IF(AND(G5=0,OR(J5=0,J5="n/a")),"Reconciled","CHECK") -> Reconciled | L5: PDF statement 01/09–30/09/2025
A6: 2025-10 | B6: =F5 -> 4682 | C6: =SUMIFS('Monzo Transactions'!$H:$H,'Monzo Transactions'!$B:$B,$A6) -> 5550 | D6: =SUMIFS('Monzo Transactions'!$I:$I,'Monzo Transactions'!$B:$B,$A6) -> 7800.41 | E6: =B6+C6-D6 -> 2431.59 | F6: 2431.59 | G6: =ROUND(E6-F6,2) -> 0 | H6: 5550 | I6: 7800.41 | J6: =ROUND((C6-H6)+(D6-I6),2) -> 0 | K6: =IF(AND(G6=0,OR(J6=0,J6="n/a")),"Reconciled","CHECK") -> Reconciled | L6: PDF statement 01/10–31/10/2025
A7: 2025-11 | B7: =F6 -> 2431.59 | C7: =SUMIFS('Monzo Transactions'!$H:$H,'Monzo Transactions'!$B:$B,$A7) -> 1000 | D7: =SUMIFS('Monzo Transactions'!$I:$I,'Monzo Transactions'!$B:$B,$A7) -> 3300.41 | E7: =B7+C7-D7 -> 131.18 | F7: 131.18 | G7: =ROUND(E7-F7,2) -> 0 | H7: 1000 | I7: 3300.41 | J7: =ROUND((C7-H7)+(D7-I7),2) -> 0 | K7: =IF(AND(G7=0,OR(J7=0,J7="n/a")),"Reconciled","CHECK") -> Reconciled | L7: PDF statement 01/11–30/11/2025
A8: 2025-12 | B8: =F7 -> 131.18 | C8: =SUMIFS('Monzo Transactions'!$H:$H,'Monzo Transactions'!$B:$B,$A8) -> 5300 | D8: =SUMIFS('Monzo Transactions'!$I:$I,'Monzo Transactions'!$B:$B,$A8) -> 3500.41 | E8: =B8+C8-D8 -> 1930.77 | F8: 1930.77 | G8: =ROUND(E8-F8,2) -> 0 | J8: n/a | K8: =IF(AND(G8=0,OR(J8=0,J8="n/a")),"Reconciled","CHECK") -> Reconciled | L8: Monzo export – last balance in month (no PDF)
A9: 2026-01 | B9: =F8 -> 1930.77 | C9: =SUMIFS('Monzo Transactions'!$H:$H,'Monzo Transactions'!$B:$B,$A9) -> 2400 | D9: =SUMIFS('Monzo Transactions'!$I:$I,'Monzo Transactions'!$B:$B,$A9) -> 3300.41 | E9: =B9+C9-D9 -> 1030.36 | F9: 1030.36 | G9: =ROUND(E9-F9,2) -> 0 | J9: n/a | K9: =IF(AND(G9=0,OR(J9=0,J9="n/a")),"Reconciled","CHECK") -> Reconciled | L9: Monzo export – last balance in month (no PDF)
A10: 2026-02 | B10: =F9 -> 1030.36 | C10: =SUMIFS('Monzo Transactions'!$H:$H,'Monzo Transactions'!$B:$B,$A10) -> 2400 | D10: =SUMIFS('Monzo Transactions'!$I:$I,'Monzo Transactions'!$B:$B,$A10) -> 3300.41 | E10: =B10+C10-D10 -> 129.95 | F10: 129.95 | G10: =ROUND(E10-F10,2) -> 0 | J10: n/a | K10: =IF(AND(G10=0,OR(J10=0,J10="n/a")),"Reconciled","CHECK") -> Reconciled | L10: Monzo export – last balance to 17/02/2026 (no PDF)
A11: Total | C11: =SUM(C5:C10) -> 24332 | D11: =SUM(D5:D10) -> 24202.05 | E11: =B5+C11-D11 -> 129.95 | F11: =F10 -> 129.95 | G11: =ROUND(E11-F11,2) -> 0
A13: Rows with a running-balance mismatch: | D13: =COUNTIF('Monzo Transactions'!M2:M37,"<>0") -> 0

Sheet Monzo Transactions
A1: Date | B1: Month | C1: Type | D1: Name | E1: Reference | F1: Monzo Category | G1: Category | H1: Money In (£) | I1: Money Out (£) | J1: Amount (£) | K1: Running Balance (£) | L1: Statement Balance (£) | M1: Difference (£) | N1: Source
A2: 45919 | B2: =TEXT(A2,"yyyy-mm") -> 2025-09 | C2: Faster payment | D2: THE KULTURE BAR AN | E2: loans | F2: Income | G2: Loans received | H2: =IF(J2>0,J2,0) -> 5000 | I2: =IF(J2<0,-J2,0) -> 0 | J2: 5000 | K2: =J2 -> 5000 | L2: 5000 | M2: =ROUND(K2-L2,2) -> 0 | N2: PDF statement Sep-2025
A3: 45919 | B3: =TEXT(A3,"yyyy-mm") -> 2025-09 | C3: Faster payment | D3: THE KULTURE BAR AN | E3: LOANS | F3: Income | G3: Loans received | H3: =IF(J3>0,J3,0) -> 1400 | I3: =IF(J3<0,-J3,0) -> 0 | J3: 1400 | K3: =K2+J3 -> 6400 | L3: 6400 | M3: =ROUND(K3-L3,2) -> 0 | N3: PDF statement Sep-2025
A4: 45921 | B4: =TEXT(A4,"yyyy-mm") -> 2025-09 | C4: Faster payment | D4: FRANCK ERIC NJIAGA | E4: CHASE | F4: Income | G4: Other income received | H4: =IF(J4>0,J4,0) -> 1282 | I4: =IF(J4<0,-J4,0) -> 0 | J4: 1282 | K4: =K3+J4 -> 7682 | L4: 7682 | M4: =ROUND(K4-L4,2) -> 0 | N4: PDF statement Sep-2025
A5: 45922 | B5: =TEXT(A5,"yyyy-mm") -> 2025-09 | C5: Faster payment | D5: Seyat Can | E5: Material | F5: Services | G5: Building materials (Seyat Can) | H5: =IF(J5>0,J5,0) -> 0 | I5: =IF(J5<0,-J5,0) -> 3000 | J5: -3000 | K5: =K4+J5 -> 4682 | L5: 4682 | M5: =ROUND(K5-L5,2) -> 0 | N5: PDF statement Sep-2025
A6: 45931 | B6: =TEXT(A6,"yyyy-mm") -> 2025-10 | C6: Faster payment | D6: Seyat Can | E6: Material | F6: Services | G6: Building materials (Seyat Can) | H6: =IF(J6>0,J6,0) -> 0 | I6: =IF(J6<0,-J6,0) -> 1500 | J6: -1500 | K6: =K5+J6 -> 3182 | L6: 3182 | M6: =ROUND(K6-L6,2) -> 0 | N6: Monzo export + PDF statement
A7: 45936 | B7: =TEXT(A7,"yyyy-mm") -> 2025-10 | C7: Faster payment | D7: FRANCK ERIC NJIAGA | E7: CHASE | F7: Income | G7: Other income received | H7: =IF(J7>0,J7,0) -> 1300 | I7: =IF(J7<0,-J7,0) -> 0 | J7: 1300 | K7: =K6+J7 -> 4482 | L7: 4482 | M7: =ROUND(K7-L7,2) -> 0 | N7: Monzo export + PDF statement
A8: 45936 | B8: =TEXT(A8,"yyyy-mm") -> 2025-10 | C8: Faster payment | D8: MIRABELLE SIEWE | E8: Mirabelle | F8: Income | G8: Other income received | H8: =IF(J8>0,J8,0) -> 1250 | I8: =IF(J8<0,-J8,0) -> 0 | J8: 1250 | K8: =K7+J8 -> 5732 | L8: 5732 | M8: =ROUND(K8-L8,2) -> 0 | N8: Monzo export + PDF statement
A9: 45936 | B9: =TEXT(A9,"yyyy-mm") -> 2025-10 | C9: Faster payment | D9: GUY NOEL DEUFI | E9: guy exch | F9: Income | G9: Other income received | H9: =IF(J9>0,J9,0) -> 500 | I9: =IF(J9<0,-J9,0) -> 0 | J9: 500 | K9: =K8+J9 -> 6232 | L9: 6232 | M9: =ROUND(K9-L9,2) -> 0 | N9: Monzo export + PDF statement
A10: 45937 | B10: =TEXT(A10,"yyyy-mm") -> 2025-10 | C10: Faster payment | D10: GUY NOEL DEUFI | E10: guy exch | F10: Income | G10: Other income received | H10: =IF(J10>0,J10,0) -> 2500 | I10: =IF(J10<0,-J10,0) -> 0 | J10: 2500 | K10: =K9+J10 -> 8732 | L10: 8732 | M10: =ROUND(K10-L10,2) -> 0 | N10: Monzo export + PDF statement
A11: 45944 | B11: =TEXT(A11,"yyyy-mm") -> 2025-10 | C11: Monzo-to-Monzo | D11: Alvine Tchega | E11: Alvine Tchega | F11: Transfers | G11: Director transfers (Alvine Tchega) | H11: =IF(J11>0,J11,0) -> 0 | I11: =IF(J11<0,-J11,0) -> 1000 | J11: -1000 | K11: =K10+J11 -> 7732 | L11: 7732 | M11: =ROUND(K11-L11,2) -> 0 | N11: Monzo export + PDF statement
A12: 45944 | B12: =TEXT(A12,"yyyy-mm") -> 2025-10 | C12: Faster payment | D12: Ahmed Sayyed | E12: Alino property Ltd | F12: Bills | G12: Payments to Alino / Ahmed Sayyed | H12: =IF(J12>0,J12,0) -> 0 | I12: =IF(J12<0,-J12,0) -> 2000 | J12: -2000 | K12: =K11+J12 -> 5732 | L12: 5732 | M12: =ROUND(K12-L12,2) -> 0 | N12: Monzo export + PDF statement
A13: 45947 | B13: =TEXT(A13,"yyyy-mm") -> 2025-10 | C13: Direct Debit | D13: Together Commercia | E13: 10395974-002 | F13: Bills | G13: Mortgage – Together Commercial (10395974-002) | H13: =IF(J13>0,J13,0) -> 0 | I13: =IF(J13<0,-J13,0) -> 2139.83 | J13: -2139.83 | K13: =K12+J13 -> 3592.17 | L13: 3592.17 | M13: =ROUND(K13-L13,2) -> 0 | N13: Monzo export + PDF statement
A14: 45947 | B14: =TEXT(A14,"yyyy-mm") -> 2025-10 | C14: Direct Debit | D14: Together Commercia | E14: 10395973-002 | F14: Bills | G14: Mortgage – Together Commercial (10395973-002) | H14: =IF(J14>0,J14,0) -> 0 | I14: =IF(J14<0,-J14,0) -> 1160.58 | J14: -1160.58 | K14: =K13+J14 -> 2431.59 | L14: 2431.59 | M14: =ROUND(K14-L14,2) -> 0 | N14: Monzo export + PDF statement
... A37: 46070 | B37: =TEXT(A37,"yyyy-mm") -> 2026-02 | C37: Direct Debit | D37: Together Commercia | E37: 10395974-002 | F37: Bills | G37: Mortgage – Together Commercial (10395974-002) | H37: =IF(J37>0,J37,0) -> 0 | I37: =IF(J37<0,-J37,0) -> 2139.83 | J37: -2139.83 | K37: =K36+J37 -> 129.95 | L37: 129.95 | M37: =ROUND(K37-L37,2) -> 0 | N37: Monzo export
G38: Total | H38: =SUM(H2:H37) -> 24332 | I38: =SUM(I2:I37) -> 24202.05 | J38: =SUM(J2:J37) -> 129.95

Sheet Monzo Categories
A1: Monzo – Totals by Category and Month (Amount: + in / − out)
A2: SUMIFS over the Monzo Transactions sheet. Change a Category there and this table follows.
A4: Category | B4: 2025-09 | C4: 2025-10 | D4: 2025-11 | E4: 2025-12 | F4: 2026-01 | G4: 2026-02 | H4: Total (£) | I4: Count | J4: Notes
A5: Building work income (Alino Ltd) | B5: =SUMIFS('Monzo Transactions'!$J:$J,'Monzo Transactions'!$G:$G,$A5,'Monzo Transactions'!$B:$B,B$4) -> 0 | C5: =SUMIFS('Monzo Transactions'!$J:$J,'Monzo Transactions'!$G:$G,$A5,'Monzo Transactions'!$B:$B,C$4) -> 0 | D5: =SUMIFS('Monzo Transactions'!$J:$J,'Monzo Transactions'!$G:$G,$A5,'Monzo Transactions'!$B:$B,D$4) -> 0 | E5: =SUMIFS('Monzo Transactions'!$J:$J,'Monzo Transactions'!$G:$G,$A5,'Monzo Transactions'!$B:$B,E$4) -> 2100 | F5: =SUMIFS('Monzo Transactions'!$J:$J,'Monzo Transactions'!$G:$G,$A5,'Monzo Transactions'!$B:$B,F$4) -> 1900 | G5: =SUMIFS('Monzo Transactions'!$J:$J,'Monzo Transactions'!$G:$G,$A5,'Monzo Transactions'!$B:$B,G$4) -> 0 | H5: =SUM(B5:G5) -> 4000 | I5: =COUNTIFS('Monzo Transactions'!$G:$G,$A5) -> 6
A6: Director transfers (Alvine Tchega) | B6: =SUMIFS('Monzo Transactions'!$J:$J,'Monzo Transactions'!$G:$G,$A6,'Monzo Transactions'!$B:$B,B$4) -> 0 | C6: =SUMIFS('Monzo Transactions'!$J:$J,'Monzo Transactions'!$G:$G,$A6,'Monzo Transactions'!$B:$B,C$4) -> -1000 | D6: =SUMIFS('Monzo Transactions'!$J:$J,'Monzo Transactions'!$G:$G,$A6,'Monzo Transactions'!$B:$B,D$4) -> 0 | E6: =SUMIFS('Monzo Transactions'!$J:$J,'Monzo Transactions'!$G:$G,$A6,'Monzo Transactions'!$B:$B,E$4) -> 2000 | F6: =SUMIFS('Monzo Transactions'!$J:$J,'Monzo Transactions'!$G:$G,$A6,'Monzo Transactions'!$B:$B,F$4) -> 200 | G6: =SUMIFS('Monzo Transactions'!$J:$J,'Monzo Transactions'!$G:$G,$A6,'Monzo Transactions'!$B:$B,G$4) -> 1400 | H6: =SUM(B6:G6) -> 2600 | I6: =COUNTIFS('Monzo Transactions'!$G:$G,$A6) -> 4 | J6: Account holder moving own money in/out.
A7: Loans received | B7: =SUMIFS('Monzo Transactions'!$J:$J,'Monzo Transactions'!$G:$G,$A7,'Monzo Transactions'!$B:$B,B$4) -> 6400 | C7: =SUMIFS('Monzo Transactions'!$J:$J,'Monzo Transactions'!$G:$G,$A7,'Monzo Transactions'!$B:$B,C$4) -> 0 | D7: =SUMIFS('Monzo Transactions'!$J:$J,'Monzo Transactions'!$G:$G,$A7,'Monzo Transactions'!$B:$B,D$4) -> 0 | E7: =SUMIFS('Monzo Transactions'!$J:$J,'Monzo Transactions'!$G:$G,$A7,'Monzo Transactions'!$B:$B,E$4) -> 0 | F7: =SUMIFS('Monzo Transactions'!$J:$J,'Monzo Transactions'!$G:$G,$A7,'Monzo Transactions'!$B:$B,F$4) -> 0 | G7: =SUMIFS('Monzo Transactions'!$J:$J,'Monzo Transactions'!$G:$G,$A7,'Monzo Transactions'!$B:$B,G$4) -> 1000 | H7: =SUM(B7:G7) -> 7400 | I7: =COUNTIFS('Monzo Transactions'!$G:$G,$A7) -> 3 | J7: Kulture Bar 'loans' (Sep) and Kakmeni J 'Loan' (Feb).
A8: Other income received | B8: =SUMIFS('Monzo Transactions'!$J:$J,'Monzo Transactions'!$G:$G,$A8,'Monzo Transactions'!$B:$B,B$4) -> 1282 | C8: =SUMIFS('Monzo Transactions'!$J:$J,'Monzo Transactions'!$G:$G,$A8,'Monzo Transactions'!$B:$B,C$4) -> 5550 | D8: =SUMIFS('Monzo Transactions'!$J:$J,'Monzo Transactions'!$G:$G,$A8,'Monzo Transactions'!$B:$B,D$4) -> 0 | E8: =SUMIFS('Monzo Transactions'!$J:$J,'Monzo Transactions'!$G:$G,$A8,'Monzo Transactions'!$B:$B,E$4) -> 0 | F8: =SUMIFS('Monzo Transactions'!$J:$J,'Monzo Transactions'!$G:$G,$A8,'Monzo Transactions'!$B:$B,F$4) -> 300 | G8: =SUMIFS('Monzo Transactions'!$J:$J,'Monzo Transactions'!$G:$G,$A8,'Monzo Transactions'!$B:$B,G$4) -> 0 | H8: =SUM(B8:G8) -> 7132 | I8: =COUNTIFS('Monzo Transactions'!$G:$G,$A8) -> 6 | J8: Njiaga (CHASE), Siewe, Deufi (guy exch), Kouchoufondjo – purpose not stated; confirm.
A9: Rent received – Kakmeni | B9: =SUMIFS('Monzo Transactions'!$J:$J,'Monzo Transactions'!$G:$G,$A9,'Monzo Transactions'!$B:$B,B$4) -> 0 | C9: =SUMIFS('Monzo Transactions'!$J:$J,'Monzo Transactions'!$G:$G,$A9,'Monzo Transactions'!$B:$B,C$4) -> 0 | D9: =SUMIFS('Monzo Transactions'!$J:$J,'Monzo Transactions'!$G:$G,$A9,'Monzo Transactions'!$B:$B,D$4) -> 1000 | E9: =SUMIFS('Monzo Transactions'!$J:$J,'Monzo Transactions'!$G:$G,$A9,'Monzo Transactions'!$B:$B,E$4) -> 1200 | F9: =SUMIFS('Monzo Transactions'!$J:$J,'Monzo Transactions'!$G:$G,$A9,'Monzo Transactions'!$B:$B,F$4) -> 0 | G9: =SUMIFS('Monzo Transactions'!$J:$J,'Monzo Transactions'!$G:$G,$A9,'Monzo Transactions'!$B:$B,G$4) -> 0 | H9: =SUM(B9:G9) -> 2200 | I9: =COUNTIFS('Monzo Transactions'!$G:$G,$A9) -> 3 | J9: Assumed rent: one payment says 'Rent'; Revolut payments from the same person treated the same. 'Loan' payment is under Loans received.
A10: Building materials (Seyat Can) | B10: =SUMIFS('Monzo Transactions'!$J:$J,'Monzo Transactions'!$G:$G,$A10,'Monzo Transactions'!$B:$B,B$4) -> -3000 | C10: =SUMIFS('Monzo Transactions'!$J:$J,'Monzo Transactions'!$G:$G,$A10,'Monzo Transactions'!$B:$B,C$4) -> -1500 | D10: =SUMIFS('Monzo Transactions'!$J:$J,'Monzo Transactions'!$G:$G,$A10,'Monzo Transactions'!$B:$B,D$4) -> 0 | E10: =SUMIFS('Monzo Transactions'!$J:$J,'Monzo Transactions'!$G:$G,$A10,'Monzo Transactions'!$B:$B,E$4) -> 0 | F10: =SUMIFS('Monzo Transactions'!$J:$J,'Monzo Transactions'!$G:$G,$A10,'Monzo Transactions'!$B:$B,F$4) -> 0 | G10: =SUMIFS('Monzo Transactions'!$J:$J,'Monzo Transactions'!$G:$G,$A10,'Monzo Transactions'!$B:$B,G$4) -> 0 | H10: =SUM(B10:G10) -> -4500 | I10: =COUNTIFS('Monzo Transactions'!$G:$G,$A10) -> 2
A11: Mortgage – Together Commercial (10395973-002) | B11: =SUMIFS('Monzo Transactions'!$J:$J,'Monzo Transactions'!$G:$G,$A11,'Monzo Transactions'!$B:$B,B$4) -> 0 | C11: =SUMIFS('Monzo Transactions'!$J:$J,'Monzo Transactions'!$G:$G,$A11,'Monzo Transactions'!$B:$B,C$4) -> -1160.58 | D11: =SUMIFS('Monzo Transactions'!$J:$J,'Monzo Transactions'!$G:$G,$A11,'Monzo Transactions'!$B:$B,D$4) -> -1160.58 | E11: =SUMIFS('Monzo Transactions'!$J:$J,'Monzo Transactions'!$G:$G,$A11,'Monzo Transactions'!$B:$B,E$4) -> -1160.58 | F11: =SUMIFS('Monzo Transactions'!$J:$J,'Monzo Transactions'!$G:$G,$A11,'Monzo Transactions'!$B:$B,F$4) -> -1160.58 | G11: =SUMIFS('Monzo Transactions'!$J:$J,'Monzo Transactions'!$G:$G,$A11,'Monzo Transactions'!$B:$B,G$4) -> -1160.58 | H11: =SUM(B11:G11) -> -5802.9 | I11: =COUNTIFS('Monzo Transactions'!$G:$G,$A11) -> 5
A12: Mortgage – Together Commercial (10395974-002) | B12: =SUMIFS('Monzo Transactions'!$J:$J,'Monzo Transactions'!$G:$G,$A12,'Monzo Transactions'!$B:$B,B$4) -> 0 | C12: =SUMIFS('Monzo Transactions'!$J:$J,'Monzo Transactions'!$G:$G,$A12,'Monzo Transactions'!$B:$B,C$4) -> -2139.83 | D12: =SUMIFS('Monzo Transactions'!$J:$J,'Monzo Transactions'!$G:$G,$A12,'Monzo Transactions'!$B:$B,D$4) -> -2139.83 | E12: =SUMIFS('Monzo Transactions'!$J:$J,'Monzo Transactions'!$G:$G,$A12,'Monzo Transactions'!$B:$B,E$4) -> -2139.83 | F12: =SUMIFS('Monzo Transactions'!$J:$J,'Monzo Transactions'!$G:$G,$A12,'Monzo Transactions'!$B:$B,F$4) -> -2139.83 | G12: =SUMIFS('Monzo Transactions'!$J:$J,'Monzo Transactions'!$G:$G,$A12,'Monzo Transactions'!$B:$B,G$4) -> -2139.83 | H12: =SUM(B12:G12) -> -10699.15 | I12: =COUNTIFS('Monzo Transactions'!$G:$G,$A12) -> 5
A13: Payments to Alino / Ahmed Sayyed | B13: =SUMIFS('Monzo Transactions'!$J:$J,'Monzo Transactions'!$G:$G,$A13,'Monzo Transactions'!$B:$B,B$4) -> 0 | C13: =SUMIFS('Monzo Transactions'!$J:$J,'Monzo Transactions'!$G:$G,$A13,'Monzo Transactions'!$B:$B,C$4) -> -2000 | D13: =SUMIFS('Monzo Transactions'!$J:$J,'Monzo Transactions'!$G:$G,$A13,'Monzo Transactions'!$B:$B,D$4) -> 0 | E13: =SUMIFS('Monzo Transactions'!$J:$J,'Monzo Transactions'!$G:$G,$A13,'Monzo Transactions'!$B:$B,E$4) -> -200 | F13: =SUMIFS('Monzo Transactions'!$J:$J,'Monzo Transactions'!$G:$G,$A13,'Monzo Transactions'!$B:$B,F$4) -> 0 | G13: =SUMIFS('Monzo Transactions'!$J:$J,'Monzo Transactions'!$G:$G,$A13,'Monzo Transactions'!$B:$B,G$4) -> 0 | H13: =SUM(B13:G13) -> -2200 | I13: =COUNTIFS('Monzo Transactions'!$G:$G,$A13) -> 2 | J13: Ahmed Sayyed payment had reference 'Alino property Ltd'.
A14: Net movement | B14: =SUM(B5:B13) -> 4682 | C14: =SUM(C5:C13) -> -2250.41 | D14: =SUM(D5:D13) -> -2300.41 | E14: =SUM(E5:E13) -> 1799.59 | F14: =SUM(F5:F13) -> -900.41 | G14: =SUM(G5:G13) -> -900.41 | H14: =SUM(H5:H13) -> 129.95 | I14: =SUM(I5:I13) -> 36
A15: Check vs reconciliation (should be 0) | B15: =ROUND(B14-('Monzo Reconciliation'!C5-'Monzo Reconciliation'!D5),2) -> 0 | C15: =ROUND(C14-('Monzo Reconciliation'!C6-'Monzo Reconciliation'!D6),2) -> 0 | D15: =ROUND(D14-('Monzo Reconciliation'!C7-'Monzo Reconciliation'!D7),2) -> 0 | E15: =ROUND(E14-('Monzo Reconciliation'!C8-'Monzo Reconciliation'!D8),2) -> 0 | F15: =ROUND(F14-('Monzo Reconciliation'!C9-'Monzo Reconciliation'!D9),2) -> 0 | G15: =ROUND(G14-('Monzo Reconciliation'!C10-'Monzo Reconciliation'!D10),2) -> 0
