Workbook

Sheet Summary
A1: Rent Split – Total per Property
A2: Totals are SUMIFS formulas over the Transactions sheet; change a row's Property there to move it.
A4: Property / Rent | B4: Payee | C4: Payments | D4: Standing Orders (£) | E4: Transfers / Card (£) | F4: Total (£) | G4: Notes
A5: FGN356 | B5: JLA | C5: =COUNTIFS(Transactions!$E:$E,$A5) -> 12 | D5: =SUMIFS(Transactions!$D:$D,Transactions!$E:$E,$A5,Transactions!$F:$F,"Standing Order") -> 8400 | E5: =F5-D5 -> 16100 | F5: =SUMIFS(Transactions!$D:$D,Transactions!$E:$E,$A5) -> 24500
A6: GBN234 | B6: House Mate Hunter | C6: =COUNTIFS(Transactions!$E:$E,$A6) -> 7 | D6: =SUMIFS(Transactions!$D:$D,Transactions!$E:$E,$A6,Transactions!$F:$F,"Standing Order") -> 15000 | E6: =F6-D6 -> 2494 | F6: =SUMIFS(Transactions!$D:$D,Transactions!$E:$E,$A6) -> 17494 | G6: Includes one-off transfer of £2,494
A7: GBN139 | B7: Housematehunter | C7: =COUNTIFS(Transactions!$E:$E,$A7) -> 12 | D7: =SUMIFS(Transactions!$D:$D,Transactions!$E:$E,$A7,Transactions!$F:$F,"Standing Order") -> 14400 | E7: =F7-D7 -> 0 | F7: =SUMIFS(Transactions!$D:$D,Transactions!$E:$E,$A7) -> 14400
A8: 74 Eastleigh Rent | B8: Victoria Frimpong | C8: =COUNTIFS(Transactions!$E:$E,$A8) -> 12 | D8: =SUMIFS(Transactions!$D:$D,Transactions!$E:$E,$A8,Transactions!$F:$F,"Standing Order") -> 14400 | E8: =F8-D8 -> 0 | F8: =SUMIFS(Transactions!$D:$D,Transactions!$E:$E,$A8) -> 14400
A9: Cheriton Rent | B9: Victoria Frimpong | C9: =COUNTIFS(Transactions!$E:$E,$A9) -> 12 | D9: =SUMIFS(Transactions!$D:$D,Transactions!$E:$E,$A9,Transactions!$F:$F,"Standing Order") -> 13800 | E9: =F9-D9 -> 0 | F9: =SUMIFS(Transactions!$D:$D,Transactions!$E:$E,$A9) -> 13800
A10: GBN227 | B10: House Mate Hunter | C10: =COUNTIFS(Transactions!$E:$E,$A10) -> 6 | D10: =SUMIFS(Transactions!$D:$D,Transactions!$E:$E,$A10,Transactions!$F:$F,"Standing Order") -> 13200 | E10: =F10-D10 -> 0 | F10: =SUMIFS(Transactions!$D:$D,Transactions!$E:$E,$A10) -> 13200
A11: Houston Rent | B11: Frimp Estates Ltd | C11: =COUNTIFS(Transactions!$E:$E,$A11) -> 6 | D11: =SUMIFS(Transactions!$D:$D,Transactions!$E:$E,$A11,Transactions!$F:$F,"Standing Order") -> 2700 | E11: =F11-D11 -> 10440 | F11: =SUMIFS(Transactions!$D:$D,Transactions!$E:$E,$A11) -> 13140
A12: OLR240164 / 76 Eastleigh | B12: Oliver Rayns Ltd | C12: =COUNTIFS(Transactions!$E:$E,$A12) -> 6 | D12: =SUMIFS(Transactions!$D:$D,Transactions!$E:$E,$A12,Transactions!$F:$F,"Standing Order") -> 4800 | E12: =F12-D12 -> 3450 | F12: =SUMIFS(Transactions!$D:$D,Transactions!$E:$E,$A12) -> 8250 | G12: Assumed same property: 76 Eastleigh £1,850 + OLR240164 £6,400 if separate
A13: F9 Rent | B13: Desmond Frimpong | C13: =COUNTIFS(Transactions!$E:$E,$A13) -> 12 | D13: =SUMIFS(Transactions!$D:$D,Transactions!$E:$E,$A13,Transactions!$F:$F,"Standing Order") -> 7500 | E13: =F13-D13 -> 0 | F13: =SUMIFS(Transactions!$D:$D,Transactions!$E:$E,$A13) -> 7500 | G13: £600/month rising to £700 from Jan 2026
A14: O18R-ARCH | B14: Hall & Home Lettings | C14: =COUNTIFS(Transactions!$E:$E,$A14) -> 4 | D14: =SUMIFS(Transactions!$D:$D,Transactions!$E:$E,$A14,Transactions!$F:$F,"Standing Order") -> 3600 | E14: =F14-D14 -> 1301.92 | F14: =SUMIFS(Transactions!$D:$D,Transactions!$E:$E,$A14) -> 4901.92
A15: 18 Oxford Rent | B15: Yogendra Navalshan | C15: =COUNTIFS(Transactions!$E:$E,$A15) -> 1 | D15: =SUMIFS(Transactions!$D:$D,Transactions!$E:$E,$A15,Transactions!$F:$F,"Standing Order") -> 1800 | E15: =F15-D15 -> 0 | F15: =SUMIFS(Transactions!$D:$D,Transactions!$E:$E,$A15) -> 1800
A16: Rent subtotal | C16: =SUM(C5:C15) -> 90 | D16: =SUM(D5:D15) -> 99600 | E16: =SUM(E5:E15) -> 33785.92 | F16: =SUM(F5:F15) -> 133385.92
A17: Other payments (not rent)
A18: Goodlord (property not named) | B18: Goodlord / Oh Goodlord Ltd | C18: =COUNTIFS(Transactions!$E:$E,$A18) -> 4 | D18: =SUMIFS(Transactions!$D:$D,Transactions!$E:$E,$A18,Transactions!$F:$F,"Standing Order") -> 0 | E18: =F18-D18 -> 7712 | F18: =SUMIFS(Transactions!$D:$D,Transactions!$E:$E,$A18) -> 7712 | G18: No property in reference – likely deposit/move-in costs; reassign on Transactions sheet
A19: IW Group Services UK (not rent) | B19: IW Group Services UK | C19: =COUNTIFS(Transactions!$E:$E,$A19) -> 5 | D19: =SUMIFS(Transactions!$D:$D,Transactions!$E:$E,$A19,Transactions!$F:$F,"Standing Order") -> 0 | E19: =F19-D19 -> 1511.47 | F19: =SUMIFS(Transactions!$D:$D,Transactions!$E:$E,$A19) -> 1511.47 | G19: Not rent – excluded from rent subtotal
A21: Grand total | C21: =C16+SUM(C18:C19) -> 99 | D21: =D16+SUM(D18:D19) -> 99600 | E21: =E16+SUM(E18:E19) -> 43009.39 | F21: =F16+SUM(F18:F19) -> 142609.39
A22: Check vs Transactions total | F22: =F21-Transactions!D101 -> 0

Sheet Transactions
A1: Date | B1: Reference | C1: Details | D1: Expense (£) | E1: Property / Rent | F1: Type
A2: 46001 | B2: PAY 003101 | C2: Standing Order Yogendra Navalshan, 18 OXFORD RENT | D2: 1800 | E2: 18 Oxford Rent | F2: Standing Order
A3: 45748 | B3: PAY 003052 | C3: Standing Order Victoria Frimpong, 74 EASTLEIGH RENT | D3: 1200 | E3: 74 Eastleigh Rent | F3: Standing Order
A4: 45778 | B4: PAY 003056 | C4: Standing Order Victoria Frimpong, 74 EASTLEIGH RENT | D4: 1200 | E4: 74 Eastleigh Rent | F4: Standing Order
A5: 45810 | B5: PAY 003063 | C5: Standing Order Victoria Frimpong, 74 EASTLEIGH RENT | D5: 1200 | E5: 74 Eastleigh Rent | F5: Standing Order
A6: 45839 | B6: PAY 003066 | C6: Standing Order Victoria Frimpong, 74 EASTLEIGH RENT | D6: 1200 | E6: 74 Eastleigh Rent | F6: Standing Order
A7: 45870 | B7: PAY 003070 | C7: Standing Order Victoria Frimpong, 74 EASTLEIGH RENT | D7: 1200 | E7: 74 Eastleigh Rent | F7: Standing Order
A8: 45901 | B8: PAY 003078 | C8: Standing Order Victoria Frimpong, 74 EASTLEIGH RENT | D8: 1200 | E8: 74 Eastleigh Rent | F8: Standing Order
A9: 45931 | B9: PAY 003082 | C9: Standing Order Victoria Frimpong, 74 EASTLEIGH RENT | D9: 1200 | E9: 74 Eastleigh Rent | F9: Standing Order
A10: 45964 | B10: PAY 003090 | C10: Standing Order Victoria Frimpong, 74 EASTLEIGH RENT | D10: 1200 | E10: 74 Eastleigh Rent | F10: Standing Order
A11: 45992 | B11: PAY 003097 | C11: Standing Order Victoria Frimpong, 74 EASTLEIGH RENT | D11: 1200 | E11: 74 Eastleigh Rent | F11: Standing Order
A12: 46024 | B12: PAY 003109 | C12: Standing Order Victoria Frimpong, 74 EASTLEIGH RENT | D12: 1200 | E12: 74 Eastleigh Rent | F12: Standing Order
A13: 46055 | B13: PAY 003118 | C13: Standing Order Victoria Frimpong, 74 EASTLEIGH RENT | D13: 1200 | E13: 74 Eastleigh Rent | F13: Standing Order
... A100: 46090 | B100: PAY 003132 | C100: Standing Order Oliver Rayns Limit, OLR240164 | D100: 1600 | E100: OLR240164 / 76 Eastleigh | F100: Standing Order
C101: Total | D101: =SUM(D2:D100) -> 142609.39
